Multiplyer/multiplier.v
module multiplier (
    input [31:0] A, B,       // IEEE 754 inputs
    input control, reset,     // Control and reset signals
    output reg [31:0] out,    // IEEE 754 result
    output reg exception      // Exception flag
);
    // Internal signals for IEEE 754 decomposition
    reg sign_A, sign_B, sign_out;  // Signs
    reg [7:0] exp_A, exp_B, exp_out;  // Exponents
    reg [23:0] mant_A, mant_B;  // 24-bit mantissas with implied 1
    reg [47:0] product;  // Product from Booth's multiplication

    // Booth’s multiplication logic for mantissas (unsigned)
    function [47:0] booth_multiply(input [23:0] m1, input [23:0] m2);
        reg [47:0] P;  // Partial product
        integer i;
        begin
            P = 0;
            for (i = 0; i < 24; i = i + 1) begin
                if (m2[i])  // If multiplier bit is 1, add shifted multiplicand
                    P = P + (m1 << i);
            end
            booth_multiply = P;  // Return the final product
        end
    endfunction

    // Main logic: IEEE-754 multiplication using Booth’s algorithm
    always @(posedge control or posedge reset) begin
        if (reset) begin
            out <= 32'b0;
            exception <= 0;
        end else begin
            // Step 1: Decompose inputs A and B
            sign_A = A[31];
            sign_B = B[31];
            exp_A = A[30:23];
            exp_B = B[30:23];
            mant_A = {1'b1, A[22:0]};  // Add implied leading 1
            mant_B = {1'b1, B[22:0]};  // Add implied leading 1

            // Step 2: Compute output sign (XOR for signs)
            sign_out = sign_A ^ sign_B;

            // Step 3: Compute exponent
            exp_out = exp_A + exp_B - 127;

            // Step 4: Multiply mantissas using Booth’s algorithm
            product = booth_multiply(mant_A, mant_B);

            // Step 5: Normalize the product (shift if necessary)
            if (product[47]) begin
                out[22:0] = product[46:24];  // Take top 23 bits
                exp_out = exp_out + 1;       // Adjust exponent
            end else begin
                out[22:0] = product[45:23];  // Take top 23 bits
            end
            
            // Step 6: Assemble the IEEE-754 result
            out[31] = sign_out;
            out[30:23] = exp_out;

            // Step 7: Check for exceptions (overflow)
            exception = (exp_out >= 255) ? 1 : 0;
        end
    end
endmodule

Multiplyer/multiplier_tb.v
`timescale 10ns / 1ns
`include "multiplier.v"

module multiplier_tb;
    reg [31:0] A, B;         // Inputs to the multiplier
    reg control, reset;       // Control and reset signals
    wire [31:0] out;          // Output from the multiplier
    wire exception;           // Exception signal

    // Instantiate the multiplier module
    multiplier uut (
        .A(A),
        .B(B),
        .control(control),
        .reset(reset),
        .out(out),
        .exception(exception)
    );

    // Clock generation for control signal
    initial begin
        control = 0;
        forever #10 control = ~control;  // Toggle every 10ns
    end

    // Test procedure
    initial begin
        $dumpfile("multiplier_tb.vcd");
        $dumpvars(0, multiplier_tb);

        // Initialize inputs and reset
        reset = 1;
        #5 reset = 0;

        // Test Case 1: A = 0.82, B = 1.23
        #10 A = 32'h3FD3CD36;  // IEEE 754 for 0.82
            B = 32'h3F9E46F1;  // IEEE 754 for 1.23
        #20;

        A = 32'h3E800000;  // IEEE 754 for 0.25
        B = 32'h40000000;  // IEEE 754 for 2.0
        #20;

        // 2nd test: A = 1.25, B = 4.0
        A = 32'h3FA00000;  // IEEE 754 for 1.25
        B = 32'h40800000;  // IEEE 754 for 4.0
        #20;

        A = 32'h40800000;  // IEEE 754 for 1.25
        B = 32'h3FA00000;  // IEEE 754 for 4.0
        #20;

        A = 32'h7f800000;  // IEEE 754 for 1.25
        B = 32'h3f9e46f1;  // IEEE 754 for 4.0
        #20;
        // Additional Test Cases
        A = 32'h40000000;  // 2.0
        B = 32'h40400000;  // 3.0
        #20;

        A = 32'hc0aa624e;  // 1.0
        B = 32'hc016a7f0;  // 1.0
        #20;


        $finish;
    end

    // Monitor output and exceptions
    initial begin
        $monitor("Time: %0t | A: %h | B: %h | Out: %h | Exception: %b", 
                 $time, A, B, out, exception);
    end
endmodule

Multiplyer/multiplier_tb.vcd
$date
	Thu Oct 24 21:28:21 2024
$end
$version
	Icarus Verilog
$end
$timescale
	1ns
$end
$scope module multiplier_tb $end
$var wire 32 ! out [31:0] $end
$var wire 1 " exception $end
$var reg 32 # A [31:0] $end
$var reg 32 $ B [31:0] $end
$var reg 1 % control $end
$var reg 1 & reset $end
$scope module uut $end
$var wire 32 ' A [31:0] $end
$var wire 32 ( B [31:0] $end
$var wire 1 % control $end
$var wire 1 & reset $end
$var reg 1 " exception $end
$var reg 8 ) exp_A [7:0] $end
$var reg 8 * exp_B [7:0] $end
$var reg 8 + exp_out [7:0] $end
$var reg 24 , mant_A [23:0] $end
$var reg 24 - mant_B [23:0] $end
$var reg 32 . out [31:0] $end
$var reg 48 / product [47:0] $end
$var reg 1 0 sign_A $end
$var reg 1 1 sign_B $end
$var reg 1 2 sign_out $end
$scope function booth_multiply $end
$var reg 48 3 P [47:0] $end
$var reg 24 4 m1 [23:0] $end
$var reg 24 5 m2 [23:0] $end
$var integer 32 6 i [31:0] $end
$upscope $end
$upscope $end
$upscope $end
$enddefinitions $end
$comment Show the parameter values. $end
$dumpall
$end
#0
$dumpvars
bx 6
bx 5
bx 4
bx 3
x2
x1
x0
bx /
b0 .
bx -
bx ,
bx +
bx *
bx )
bx (
bx '
1&
0%
bx $
bx #
0"
b0 !
$end
#50
0&
#100
x"
bx !
bx .
b11000 6
bx 3
b1xxxxxxxxxxxxxxxxxxxxxxx 4
b1xxxxxxxxxxxxxxxxxxxxxxx 5
b1xxxxxxxxxxxxxxxxxxxxxxx -
b1xxxxxxxxxxxxxxxxxxxxxxx ,
1%
#150
b111111100111100100011011110001 $
b111111100111100100011011110001 (
b111111110100111100110100110110 #
b111111110100111100110100110110 '
#200
0%
#300
0"
b1000000000000101111001101011000 !
b1000000000000101111001101011000 .
b100000101111001101011000110101001111001111010110 /
b11000 6
b100000101111001101011000110101001111001111010110 3
b110100111100110100110110 4
b100111100100011011110001 5
b10000000 +
02
b100111100100011011110001 -
b110100111100110100110110 ,
b1111111 *
b1111111 )
01
00
1%
#350
b1000000000000000000000000000000 $
b1000000000000000000000000000000 (
b111110100000000000000000000000 #
b111110100000000000000000000000 '
#400
0%
#500
b111111000000000000000000000000 !
b111111000000000000000000000000 .
b10000000000000000000000000000000000000000000000 /
b11000 6
b10000000000000000000000000000000000000000000000 3
b100000000000000000000000 4
b100000000000000000000000 5
b1111110 +
b100000000000000000000000 -
b100000000000000000000000 ,
b10000000 *
b1111101 )
1%
#550
b1000000100000000000000000000000 $
b1000000100000000000000000000000 (
b111111101000000000000000000000 #
b111111101000000000000000000000 '
#600
0%
#700
b1000000101000000000000000000000 !
b1000000101000000000000000000000 .
b10100000000000000000000000000000000000000000000 /
b11000 6
b10100000000000000000000000000000000000000000000 3
b101000000000000000000000 4
b10000001 +
b101000000000000000000000 ,
b10000001 *
b1111111 )
1%
#750
b111111101000000000000000000000 $
b111111101000000000000000000000 (
b1000000100000000000000000000000 #
b1000000100000000000000000000000 '
#800
0%
#900
b11000 6
b10100000000000000000000000000000000000000000000 3
b100000000000000000000000 4
b101000000000000000000000 5
b101000000000000000000000 -
b100000000000000000000000 ,
b1111111 *
b10000001 )
1%
#950
b111111100111100100011011110001 $
b111111100111100100011011110001 (
b1111111100000000000000000000000 #
b1111111100000000000000000000000 '
#1000
0%
#1100
1"
b1111111100111100100011011110001 !
b1111111100111100100011011110001 .
b10011110010001101111000100000000000000000000000 /
b11000 6
b10011110010001101111000100000000000000000000000 3
b100111100100011011110001 5
b11111111 +
b100111100100011011110001 -
b11111111 )
1%
#1150
b1000000010000000000000000000000 $
b1000000010000000000000000000000 (
b1000000000000000000000000000000 #
b1000000000000000000000000000000 '
#1200
0%
#1300
0"
b1000000110000000000000000000000 !
b1000000110000000000000000000000 .
b11000000000000000000000000000000000000000000000 /
b11000 6
b11000000000000000000000000000000000000000000000 3
b110000000000000000000000 5
b10000001 +
b110000000000000000000000 -
b10000000 *
b10000000 )
1%
#1350
b11000000000101101010011111110000 $
b11000000000101101010011111110000 (
b11000000101010100110001001001110 #
b11000000101010100110001001001110 '
#1400
0%
#1500
b1000001010010001000101010111111 !
b1000001010010001000101010111111 .
b11001000100010101011111100100010000101100100000 /
b11000 6
b11001000100010101011111100100010000101100100000 3
b101010100110001001001110 4
b100101101010011111110000 5
b10000010 +
b100101101010011111110000 -
b101010100110001001001110 ,
b10000001 )
11
10
1%
