ALU_master/HexDisplay.v
module HexDisplay(
    input wire clk,              // 50 MHz clock signal
    input wire reset,            // Reset signal
    input wire [31:0] number,    // 32-bit input number
    output reg [6:0] digit7,     // Segments for display 7 (most significant digit)
    output reg [6:0] digit6,     // Segments for display 6
    output reg [6:0] digit5,     // Segments for display 5
    output reg [6:0] digit4,     // Segments for display 4
    output reg [6:0] digit3,     // Segments for display 3
    output reg [6:0] digit2,     // Segments for display 2
    output reg [6:0] digit1,     // Segments for display 1
    output reg [6:0] digit0,     // Segments for display 0 (least significant digit)
    output reg [31:0] debug_number // Debug output to monitor the input
);          // Slower clock at 60 Hz

    // Hexadecimal to seven-segment decoder
    function [6:0] hex_to_segments;
        input [3:0] hex;
        begin
            case (hex)
                4'h0: hex_to_segments = 7'b1000000;
                4'h1: hex_to_segments = 7'b1111001;
                4'h2: hex_to_segments = 7'b0100100;
                4'h3: hex_to_segments = 7'b0110000;
                4'h4: hex_to_segments = 7'b0011001;
                4'h5: hex_to_segments = 7'b0010010;
                4'h6: hex_to_segments = 7'b0000010;
                4'h7: hex_to_segments = 7'b1111000;
                4'h8: hex_to_segments = 7'b0000000;
                4'h9: hex_to_segments = 7'b0010000;
                4'hA: hex_to_segments = 7'b0001000;
                4'hB: hex_to_segments = 7'b0000011;
                4'hC: hex_to_segments = 7'b1000110;
                4'hD: hex_to_segments = 7'b0100001;
                4'hE: hex_to_segments = 7'b0000110;
                4'hF: hex_to_segments = 7'b0001110;
                default: hex_to_segments = 7'b1111111; // All segments off
            endcase
        end
    endfunction

    // Update the current digit and assign values to the outputs
    always@(*) begin
        if (reset) begin
            digit7 <= 7'b1111111;
            digit6 <= 7'b1111111;
            digit5 <= 7'b1111111;
            digit4 <= 7'b1111111;
            digit3 <= 7'b1111111;
            digit2 <= 7'b1111111;
            digit1 <= 7'b1111111;
            digit0 <= 7'b1111111;
            debug_number <= 32'b0; // Clear debug value on reset
        end else begin
            digit0 <= hex_to_segments(number[3:0]);
            digit1 <= hex_to_segments(number[7:4]);
            digit2 <= hex_to_segments(number[11:8]);
            digit3 <= hex_to_segments(number[15:12]);
            digit4 <= hex_to_segments(number[19:16]);
            digit5 <= hex_to_segments(number[23:20]);
            digit6 <= hex_to_segments(number[27:24]);
            digit7 <= hex_to_segments(number[31:28]);
            debug_number <= number; // Update debug value with input
        end
    end

endmodule

ALU_master/divider.v
module divider (
    input [31:0] DD,    // Dividend in IEEE-754
    input [31:0] DS,    // Divisor in IEEE-754
    input control,      // Trigger on positive edge
    input reset,        // Reset process on positive edge
    output reg [31:0] out,      // IEEE-754 formatted result
    output reg exception,       // Exception flag
    output reg zeroDiv          // Zero division flag
);

    // Internal registers
    reg sign;
    reg [7:0] exp_DD, exp_DS, exp_out;
    reg [23:0] mant_DD, mant_DS;
    reg [23:0] quotient;  // Quotient for mantissa division
    integer i;

    // Division function for normalized mantissas
    function [23:0] NRDivisor(
        input [23:0] D1,  // Dividend mantissa
        input [23:0] D2   // Divisor mantissa
    );
        reg [23:0] remainder;
        reg [23:0] temp_quotient;
        reg [23:0] temp_remainder;
        integer i;

        begin
            // Initialize quotient and remainder
            temp_quotient = 0;
            temp_remainder = 0;

            for (i = 23; i >= 0; i = i - 1) begin
                // Shift remainder left and bring down the next bit of dividend
                temp_remainder = (temp_remainder << 1) | D1[i];

                if (temp_remainder >= D2) begin
                    // Subtract divisor from remainder
                    temp_remainder = temp_remainder - D2;
                    // Set the i-th bit of the quotient to 1
                    temp_quotient = temp_quotient | (1 << i);
                end
            end

            // Return the computed quotient
            NRDivisor = temp_quotient;
        end
    endfunction

    // Always block triggered on control or reset signal
    always @(posedge control or posedge reset) begin
        if (reset) begin
            out <= 32'b0;
            exception <= 0;
            zeroDiv <= 0;
        end else begin
            // Step 1: Extract sign, exponent, and mantissa
            sign = DD[31] ^ DS[31];  // XOR for sign bit
            exp_DD = DD[30:23];
            exp_DS = DS[30:23];
            mant_DD = {1'b1, DD[22:0]};  // Add implicit 1 for normalized mantissa
            mant_DS = {1'b1, DS[22:0]};  // Add implicit 1 for normalized mantissa

            // Step 2: Check for divide by zero
            if (DS == 32'b0) begin
                out <= {sign, 8'hFF, 23'b0};  // Infinity
                exception <= 0;
                zeroDiv <= 1;
            end else begin
                zeroDiv <= 0;

                // Step 3: Exponent calculation
                exp_out = exp_DD - exp_DS + 127;  // Adjust bias

                // Step 4: Perform mantissa division
                quotient = NRDivisor(mant_DD, mant_DS);

                // Step 5: Normalize quotient
						for (i = 0; i < 23 && quotient[23] == 0 && exp_out > 0; i = i + 1) begin
							 quotient = quotient << 1;
							 exp_out = exp_out - 1;
						end

                // Step 6: Handle overflow/underflow
                if (exp_out >= 255) begin
                    out <= {sign, 8'hFF, 23'b0};  // Infinity
                    exception <= 1;
                end else if (exp_out <= 0) begin
                    out <= {sign, 8'b0, 23'b0};  // Zero
                    exception <= 1;
                end else begin
                    // Step 7: Remove the leading 1 in normalized mantissa for output
                    out <= {sign, exp_out[7:0], quotient[22:0]};  // Valid result
                    exception <= 0;
                end
            end
        end
    end
endmodule

Multiplyer/multiplier.v
module multiplier (
    input [31:0] A, B,       // IEEE 754 inputs
    input control, reset,     // Control and reset signals
    output reg [31:0] out,    // IEEE 754 result
    output reg exception      // Exception flag
);
    // Internal signals for IEEE 754 decomposition
    reg sign_A, sign_B, sign_out;  // Signs
    reg [7:0] exp_A, exp_B, exp_out;  // Exponents
    reg [23:0] mant_A, mant_B;  // 24-bit mantissas with implied 1
    reg [47:0] product;  // Product from Booth's multiplication

    // Booth’s multiplication logic for mantissas (unsigned)
    function [47:0] booth_multiply(input [23:0] m1, input [23:0] m2);
        reg [47:0] P;  // Partial product
        integer i;
        begin
            P = 0;
            for (i = 0; i < 24; i = i + 1) begin
                if (m2[i])  // If multiplier bit is 1, add shifted multiplicand
                    P = P + (m1 << i);
            end
            booth_multiply = P;  // Return the final product
        end
    endfunction

    // Main logic: IEEE-754 multiplication using Booth’s algorithm
    always @(posedge control or posedge reset) begin
        if (reset) begin
            out <= 32'b0;
            exception <= 0;
        end else begin
            // Step 1: Decompose inputs A and B
            sign_A = A[31];
            sign_B = B[31];
            exp_A = A[30:23];
            exp_B = B[30:23];
            mant_A = {1'b1, A[22:0]};  // Add implied leading 1
            mant_B = {1'b1, B[22:0]};  // Add implied leading 1

            // Step 2: Compute output sign (XOR for signs)
            sign_out = sign_A ^ sign_B;

            // Step 3: Compute exponent
            exp_out = exp_A + exp_B - 127;

            // Step 4: Multiply mantissas using Booth’s algorithm
            product = booth_multiply(mant_A, mant_B);

            // Step 5: Normalize the product (shift if necessary)
            if (product[47]) begin
                out[22:0] = product[46:24];  // Take top 23 bits
                exp_out = exp_out + 1;       // Adjust exponent
            end else begin
                out[22:0] = product[45:23];  // Take top 23 bits
            end
            
            // Step 6: Assemble the IEEE-754 result
            out[31] = sign_out;
            out[30:23] = exp_out;

            // Step 7: Check for exceptions (overflow)
            exception = (exp_out >= 255) ? 1 : 0;
        end
    end
endmodule

ALU_master/add_sub.v
module add_sub(
    input [31:0] A, B,         // IEEE 754 input numbers
    input control, reset, addsub, // Control, reset, and add/subtract signals
    output reg [31:0] out,     // IEEE 754 result
    output reg exception       // Exception signal
);
    // Internal signals
    reg [7:0] expA, expB, expOut;     // Exponents
    reg [24:0] mantA, mantB, mantOut; // Mantissas (with leading bits)
    reg signA, signB, signOut;        // Signs
    reg [7:0] expDiff;                // Exponent difference
    reg operation;                    // Actual operation: add (0) / subtract (1)
	 
	 integer i;

    // Sequential logic triggered by control or reset
    always @(posedge control or posedge reset) begin
        if (reset) begin
            out <= 32'h00000000;  // Reset the output
            exception <= 0;       // Reset exception flag
        end else begin
            // Step 1: Extract sign, exponent, and mantissa
            signA = A[31];
            
            if (addsub) signB = ~B[31]; // Invert sign of B if subtracting
            else signB = B[31];

            expA = A[30:23];
            expB = B[30:23];
            mantA = {2'b01, A[22:0]}; // Add leading bits to mantissa
            mantB = {2'b01, B[22:0]}; // Add leading bits to mantissa

            // Step 2: Align exponents and mantissas
            if (expA > expB) begin
                expDiff = expA - expB;
                mantB = mantB >> expDiff;
                expOut = expA;
            end else begin
                expDiff = expB - expA;
                mantA = mantA >> expDiff;
                expOut = expB;
            end

            // Step 3: Add or subtract mantissas based on signs
            if (signA == signB) begin
                // If signs are the same, perform addition
                mantOut = mantA + mantB;
                signOut = signA;
            end else begin
                // If signs differ, perform subtraction
                if (mantA >= mantB) begin
                    mantOut = mantA - mantB;
                    signOut = signA;
                end else begin
                    mantOut = mantB - mantA;
                    signOut = signB;
                end
            end

            // Step 4: Normalize the result
            if (mantOut[24]) begin
                mantOut = mantOut >> 1;
                expOut = expOut + 1;
            end else begin
					for (i = 0; i < 23 && mantOut[23] == 0 && expOut > 0; i = i + 1) begin
						mantOut = mantOut << 1;
						expOut = expOut - 1;
					end
            end

            // Step 5: Assemble the final IEEE 754 result
            out <= {signOut, expOut, mantOut[22:0]};
            exception <= (expOut == 8'hFF); // Set exception on overflow
        end
    end
endmodule

ALU_master/instructions.v
module instructions (
    input clk,
    input loadData,
    output reg [31:0] A,
    output reg [31:0] B
);
    // Memory for A and B values
    reg [31:0] A_mem [0:15];
    reg [31:0] B_mem [0:15];
    reg [3:0] index;            // Index for current data
    reg loadData_prev;          // Register to detect edge of loadData
    reg loadData_valid;         // Signal to trigger data transfer

    initial begin
        // Initialize memory

        A_mem[0] = 32'h40224dd3; B_mem[0] = 32'h3fc3d70a;
        A_mem[1] = 32'h40224dd3; B_mem[1] = 32'h3fc3d70a;
        A_mem[2] = 32'h3fc3d70a; B_mem[2] = 32'h40224dd3;
        A_mem[3] = 32'h40224dd3; B_mem[3] = 32'h3fc3d70a;
        index = 0;               // Start at first data pair
        A = 32'b0;
        B = 32'b0;
        loadData_prev = 0;
        loadData_valid = 0;
    end

    // Detect loadData edge
    always @(posedge clk) begin
        if (loadData && !loadData_prev) begin
            // Rising edge of loadData detected
            loadData_valid <= 1;
        end

        // Update loadData_prev to track edge
        loadData_prev <= loadData;

        // Load data on the first rising edge after loadData goes high
        if (loadData_valid) begin
            A <= A_mem[index];
            B <= B_mem[index];
            index <= index + 1;

            if (index == 15) begin
                index <= 0;        // Wrap around if last data is reached
            end

            loadData_valid <= 0;   // Clear valid signal after loading
        end
    end
endmodule

ALU_master/ALU_top.v
module ALU_top (
    input clk,                // Clock signal for synchronization
    input loadData,           // Load data control signal for instructions
    input control, reset,     // Control and reset signals
    input [1:0] select,       // Operation select (00: add, 01: sub, 10: mul, 11: div)
    output [6:0] digit7,      // Seven-segment display for most significant digit
    output [6:0] digit6,      // Seven-segment display
    output [6:0] digit5,      // Seven-segment display
    output [6:0] digit4,      // Seven-segment display
    output [6:0] digit3,      // Seven-segment display
    output [6:0] digit2,      // Seven-segment display
    output [6:0] digit1,      // Seven-segment display
    output [6:0] digit0,      // Seven-segment display for least significant digit
    output reg exception,     // General exception signal
    output reg zeroDiv        // Division by zero signal
);

    // Internal signals
    wire [31:0] A_wire, B_wire;         // Wires for A and B from instructions module
    wire [31:0] add_sub_out, mul_out, div_out;
    wire add_sub_exception, mul_exception, div_exception, div_zeroDiv;
    reg addsub_signal;
    reg [31:0] result;                 // To hold the ALU result

    // Instantiate the instructions module
    instructions instructions_inst (
        .clk(clk),
        .loadData(loadData),
        .A(A_wire),
        .B(B_wire)
    );

    // Instantiate add_sub module
    add_sub add_sub_inst (
        .A(A_wire),              // Use A from instructions
        .B(B_wire),              // Use B from instructions
        .control(control),
        .reset(reset),
        .addsub(addsub_signal),
        .out(add_sub_out),
        .exception(add_sub_exception)
    );

    // Instantiate multiplier module
    multiplier mul_inst (
        .A(A_wire),              // Use A from instructions
        .B(B_wire),              // Use B from instructions
        .control(control),
        .reset(reset),
        .out(mul_out),
        .exception(mul_exception)
    );

    // Instantiate divider module
    divider div_inst (
        .DD(A_wire),             // Use A from instructions
        .DS(B_wire),             // Use B from instructions
        .control(control),
        .reset(reset),
        .out(div_out),
        .exception(div_exception),
        .zeroDiv(div_zeroDiv)
    );

    // ALU Operation
    always @(posedge clk or posedge reset) begin
        if (reset) begin
            result <= 32'b0;
            exception <= 1'b0;
            zeroDiv <= 1'b0;
            addsub_signal <= 1'b0;
        end else begin
            case (select)
                2'b00: begin // Addition
                    addsub_signal <= 1'b0; // Set addsub to 0 for addition
                    result <= add_sub_out;
                    exception <= add_sub_exception;
                end
                2'b01: begin // Subtraction
                    addsub_signal <= 1'b1; // Set addsub to 1 for subtraction
                    result <= add_sub_out;
                    exception <= add_sub_exception;
                end
                2'b10: begin // Multiplication
                    result <= mul_out;
                    exception <= mul_exception;
                end
                2'b11: begin // Division
                    result <= div_out;
                    exception <= div_exception;
                    zeroDiv <= div_zeroDiv;
                end
                default: begin
                    result <= 32'b0;
                    exception <= 1'b0;
                    zeroDiv <= 1'b0;
                end
            endcase
        end
    end

    // Instantiate HexDisplay module for seven-segment output
    HexDisplay hex_display_inst (
        .clk(clk),             // Clock signal
        .number(result),       // Pass the result to be displayed
        .reset(reset),         // Reset signal
        .digit7(digit7),       // Seven-segment display for most significant digit
        .digit6(digit6),       // Seven-segment display
        .digit5(digit5),       // Seven-segment display
        .digit4(digit4),       // Seven-segment display
        .digit3(digit3),       // Seven-segment display
        .digit2(digit2),       // Seven-segment display
        .digit1(digit1),       // Seven-segment display
        .digit0(digit0)        // Seven-segment display for least significant digit
    );

endmodule

ALU_master/ALU_top_tb.v
`timescale 1ns / 1ps
`include "add_sub.v"
`include "multiplier.v"
`include "divider.v"
`include "instructions.v"
`include "ALU_top.v"
`include "hexDisplay.v"

module ALU_top_tb;
    // Clock and control signals
    reg clk;
    reg loadData;
    reg control;
    reg reset;
    reg [1:0] select;
    reg[6:0] digit7;      // Seven-segment display for most significant digit
    reg [6:0] digit6;      // Seven-segment display
    reg [6:0] digit5;      // Seven-segment display
    reg [6:0] digit4;      // Seven-segment display
    reg [6:0] digit3;      // Seven-segment display
    reg [6:0] digit2;      // Seven-segment display
    reg [6:0] digit1;      // Seven-segment display
    reg [6:0] digit0;

    // Outputs from the ALU_top module
    wire [31:0] out;
    wire exception;
    wire zeroDiv;

    // Include all modules


    // Instantiate the ALU_top module
    ALU_top uut (
        .clk(clk),
        .loadData(loadData),
        .control(control),
        .reset(reset),
        .select(select),
        .exception(exception),
        .zeroDiv(zeroDiv)
    );

    // Clock generation: 50 Hz (20 ms period)
    initial begin
        clk = 0;
        forever #10 clk = ~clk; // Toggle every 10 ms
    end

    // Simulation initialization
    initial begin
        // Initialize variables
        loadData = 0;
        control = 0;
        reset = 0;
        select = 2'b00; // Default to addition

        // Dump waveform
        $dumpfile("ALU_top_tb.vcd");
        $dumpvars(0, ALU_top_tb);

        // Reset the design
        reset = 1;
        #20; // Wait for 20 ns
        reset = 0;
        #50
        // Load first data and perform addition
        loadData = 1;
        #1000 loadData = 0;
        #100 control = 1;
        #1000 control = 0;


        // Wait and perform subtraction
        #100
        select = 2'b01;
        loadData = 1;
        #1000 loadData = 0;
        #100 control = 1;
        #1000 control = 0;

        // Wait and perform multiplication
        #100
        select = 2'b10;
        loadData = 1;
        #1000 loadData = 0;
        #100 control = 1;
        #1000 control = 0;

        // Wait and perform division
        #100
        select = 2'b11;
        loadData = 1;
        #1000 loadData = 0;
        #100 control = 1;
        #1000 control = 0;

        // Wait and finish simulation
        #200;
        $finish;
    end
endmodule

ALU_master/ALU_top_tb.vcd
$date
	Thu Dec 19 01:09:12 2024
$end
$version
	Icarus Verilog
$end
$timescale
	1ps
$end
$scope module ALU_top_tb $end
$var wire 1 ! zeroDiv $end
$var wire 1 " exception $end
$var reg 1 # clk $end
$var reg 1 $ control $end
$var reg 1 % loadData $end
$var reg 1 & reset $end
$var reg 2 ' select [1:0] $end
$scope module uut $end
$var wire 1 # clk $end
$var wire 1 $ control $end
$var wire 1 % loadData $end
$var wire 1 & reset $end
$var wire 2 ( select [1:0] $end
$var wire 32 ) mul_out [31:0] $end
$var wire 1 * mul_exception $end
$var wire 1 + div_zeroDiv $end
$var wire 32 , div_out [31:0] $end
$var wire 1 - div_exception $end
$var wire 7 . digit7 [6:0] $end
$var wire 7 / digit6 [6:0] $end
$var wire 7 0 digit5 [6:0] $end
$var wire 7 1 digit4 [6:0] $end
$var wire 7 2 digit3 [6:0] $end
$var wire 7 3 digit2 [6:0] $end
$var wire 7 4 digit1 [6:0] $end
$var wire 7 5 digit0 [6:0] $end
$var wire 32 6 add_sub_out [31:0] $end
$var wire 1 7 add_sub_exception $end
$var wire 32 8 B_wire [31:0] $end
$var wire 32 9 A_wire [31:0] $end
$var reg 1 : addsub_signal $end
$var reg 1 " exception $end
$var reg 32 ; result [31:0] $end
$var reg 1 ! zeroDiv $end
$scope module add_sub_inst $end
$var wire 1 : addsub $end
$var wire 1 $ control $end
$var wire 1 & reset $end
$var wire 32 < B [31:0] $end
$var wire 32 = A [31:0] $end
$var reg 1 7 exception $end
$var reg 8 > expA [7:0] $end
$var reg 8 ? expB [7:0] $end
$var reg 8 @ expDiff [7:0] $end
$var reg 8 A expOut [7:0] $end
$var reg 25 B mantA [24:0] $end
$var reg 25 C mantB [24:0] $end
$var reg 25 D mantOut [24:0] $end
$var reg 32 E out [31:0] $end
$var reg 1 F signA $end
$var reg 1 G signB $end
$var reg 1 H signOut $end
$var integer 32 I i [31:0] $end
$upscope $end
$scope module div_inst $end
$var wire 1 $ control $end
$var wire 1 & reset $end
$var wire 32 J DS [31:0] $end
$var wire 32 K DD [31:0] $end
$var reg 1 - exception $end
$var reg 8 L exp_DD [7:0] $end
$var reg 8 M exp_DS [7:0] $end
$var reg 8 N exp_out [7:0] $end
$var reg 24 O mant_DD [23:0] $end
$var reg 24 P mant_DS [23:0] $end
$var reg 32 Q out [31:0] $end
$var reg 24 R quotient [23:0] $end
$var reg 1 S sign $end
$var reg 1 + zeroDiv $end
$var integer 32 T i [31:0] $end
$scope function NRDivisor $end
$var reg 24 U D1 [23:0] $end
$var reg 24 V D2 [23:0] $end
$var reg 24 W temp_quotient [23:0] $end
$var reg 24 X temp_remainder [23:0] $end
$var integer 32 Y i [31:0] $end
$upscope $end
$upscope $end
$scope module hex_display_inst $end
$var wire 1 # clk $end
$var wire 32 Z number [31:0] $end
$var wire 1 & reset $end
$var reg 32 [ debug_number [31:0] $end
$var reg 7 \ digit0 [6:0] $end
$var reg 7 ] digit1 [6:0] $end
$var reg 7 ^ digit2 [6:0] $end
$var reg 7 _ digit3 [6:0] $end
$var reg 7 ` digit4 [6:0] $end
$var reg 7 a digit5 [6:0] $end
$var reg 7 b digit6 [6:0] $end
$var reg 7 c digit7 [6:0] $end
$scope function hex_to_segments $end
$var reg 4 d hex [3:0] $end
$upscope $end
$upscope $end
$scope module instructions_inst $end
$var wire 1 # clk $end
$var wire 1 % loadData $end
$var reg 32 e A [31:0] $end
$var reg 32 f B [31:0] $end
$var reg 4 g index [3:0] $end
$var reg 1 h loadData_prev $end
$var reg 1 i loadData_valid $end
$upscope $end
$scope module mul_inst $end
$var wire 32 j A [31:0] $end
$var wire 32 k B [31:0] $end
$var wire 1 $ control $end
$var wire 1 & reset $end
$var reg 1 * exception $end
$var reg 8 l exp_A [7:0] $end
$var reg 8 m exp_B [7:0] $end
$var reg 8 n exp_out [7:0] $end
$var reg 24 o mant_A [23:0] $end
$var reg 24 p mant_B [23:0] $end
$var reg 32 q out [31:0] $end
$var reg 48 r product [47:0] $end
$var reg 1 s sign_A $end
$var reg 1 t sign_B $end
$var reg 1 u sign_out $end
$scope function booth_multiply $end
$var reg 48 v P [47:0] $end
$var reg 24 w m1 [23:0] $end
$var reg 24 x m2 [23:0] $end
$var integer 32 y i [31:0] $end
$upscope $end
$upscope $end
$upscope $end
$upscope $end
$enddefinitions $end
$comment Show the parameter values. $end
$dumpall
$end
#0
$dumpvars
bx y
bx x
bx w
bx v
xu
xt
xs
bx r
b0 q
bx p
bx o
bx n
bx m
bx l
b0 k
b0 j
0i
0h
b0 g
b0 f
b0 e
bx d
b1111111 c
b1111111 b
b1111111 a
b1111111 `
b1111111 _
b1111111 ^
b1111111 ]
b1111111 \
b0 [
b0 Z
bx Y
bx X
bx W
bx V
bx U
bx T
xS
bx R
b0 Q
bx P
bx O
bx N
bx M
bx L
b0 K
b0 J
bx I
xH
xG
xF
b0 E
bx D
bx C
bx B
bx A
bx @
bx ?
bx >
b0 =
b0 <
b0 ;
0:
b0 9
b0 8
07
b0 6
b1111111 5
b1111111 4
b1111111 3
b1111111 2
b1111111 1
b1111111 0
b1111111 /
b1111111 .
0-
b0 ,
0+
0*
b0 )
b0 (
b0 '
1&
0%
0$
0#
0"
0!
$end
#10000
1#
#20000
b1000000 .
b1000000 c
b1000000 /
b1000000 b
b1000000 0
b1000000 a
b1000000 1
b1000000 `
b1000000 2
b1000000 _
b1000000 3
b1000000 ^
b1000000 4
b1000000 ]
b1000000 5
b1000000 \
b0 d
0#
0&
#30000
1#
#40000
0#
#50000
1#
#60000
0#
#70000
1h
1i
1#
1%
#80000
0#
#90000
0i
b1 g
b111111110000111101011100001010 8
b111111110000111101011100001010 <
b111111110000111101011100001010 J
b111111110000111101011100001010 f
b111111110000111101011100001010 k
b1000000001000100100110111010011 9
b1000000001000100100110111010011 =
b1000000001000100100110111010011 K
b1000000001000100100110111010011 e
b1000000001000100100110111010011 j
1#
#100000
0#
#110000
1#
#120000
0#
#130000
1#
#140000
0#
#150000
1#
#160000
0#
#170000
1#
#180000
0#
#190000
1#
#200000
0#
#210000
1#
#220000
0#
#230000
1#
#240000
0#
#250000
1#
#260000
0#
#270000
1#
#280000
0#
#290000
1#
#300000
0#
#310000
1#
#320000
0#
#330000
1#
#340000
0#
#350000
1#
#360000
0#
#370000
1#
#380000
0#
#390000
1#
#400000
0#
#410000
1#
#420000
0#
#430000
1#
#440000
0#
#450000
1#
#460000
0#
#470000
1#
#480000
0#
#490000
1#
#500000
0#
#510000
1#
#520000
0#
#530000
1#
#540000
0#
#550000
1#
#560000
0#
#570000
1#
#580000
0#
#590000
1#
#600000
0#
#610000
1#
#620000
0#
#630000
1#
#640000
0#
#650000
1#
#660000
0#
#670000
1#
#680000
0#
#690000
1#
#700000
0#
#710000
1#
#720000
0#
#730000
1#
#740000
0#
#750000
1#
#760000
0#
#770000
1#
#780000
0#
#790000
1#
#800000
0#
#810000
1#
#820000
0#
#830000
1#
#840000
0#
#850000
1#
#860000
0#
#870000
1#
#880000
0#
#890000
1#
#900000
0#
#910000
1#
#920000
0#
#930000
1#
#940000
0#
#950000
1#
#960000
0#
#970000
1#
#980000
0#
#990000
1#
#1000000
0#
#1010000
1#
#1020000
0#
#1030000
1#
#1040000
0#
#1050000
1#
#1060000
0#
#1070000
0h
1#
0%
#1080000
0#
#1090000
1#
#1100000
0#
#1110000
1#
#1120000
0#
#1130000
1#
#1140000
0#
#1150000
1#
#1160000
0#
#1170000
b110100100000000000000000000000 ,
b110100100000000000000000000000 Q
b1000000100000100001110010101100 6
b1000000100000100001110010101100 E
b10111 T
b0 R
b11111111111111111111111111111111 Y
b101000100100110111010011 X
b0 W
b101000100100110111010011 U
b110000111101011100001010 V
b1101001 N
b110000111101011100001010 P
b101000100100110111010011 O
b1111111 M
b10000000 L
0S
b1000000011110000101001100111010 )
b1000000011110000101001100111010 q
b11111000010100110011101011011000011111100111110 r
b11000 y
b11111000010100110011101011011000011111100111110 v
b101000100100110111010011 w
b110000111101011100001010 x
b10000000 n
0u
b110000111101011100001010 p
b101000100100110111010011 o
b1111111 m
b10000000 l
0t
0s
0H
b100000100001110010101100 D
b10000001 A
b1 @
b11000011110101110000101 C
b101000100100110111010011 B
b1111111 ?
b10000000 >
0G
0F
1#
1$
#1180000
0#
#1190000
b1000000100000100001110010101100 [
b11001 .
b11001 c
b0 0
b0 a
b100100 1
b100100 `
b1111001 2
b1111001 _
b1000110 3
b1000110 ^
b1000 4
b1000 ]
b1000110 5
b1000110 \
b100 d
b1000000100000100001110010101100 ;
b1000000100000100001110010101100 Z
1#
#1200000
0#
#1210000
1#
#1220000
0#
#1230000
1#
#1240000
0#
#1250000
1#
#1260000
0#
#1270000
1#
#1280000
0#
#1290000
1#
#1300000
0#
#1310000
1#
#1320000
0#
#1330000
1#
#1340000
0#
#1350000
1#
#1360000
0#
#1370000
1#
#1380000
0#
#1390000
1#
#1400000
0#
#1410000
1#
#1420000
0#
#1430000
1#
#1440000
0#
#1450000
1#
#1460000
0#
#1470000
1#
#1480000
0#
#1490000
1#
#1500000
0#
#1510000
1#
#1520000
0#
#1530000
1#
#1540000
0#
#1550000
1#
#1560000
0#
#1570000
1#
#1580000
0#
#1590000
1#
#1600000
0#
#1610000
1#
#1620000
0#
#1630000
1#
#1640000
0#
#1650000
1#
#1660000
0#
#1670000
1#
#1680000
0#
#1690000
1#
#1700000
0#
#1710000
1#
#1720000
0#
#1730000
1#
#1740000
0#
#1750000
1#
#1760000
0#
#1770000
1#
#1780000
0#
#1790000
1#
#1800000
0#
#1810000
1#
#1820000
0#
#1830000
1#
#1840000
0#
#1850000
1#
#1860000
0#
#1870000
1#
#1880000
0#
#1890000
1#
#1900000
0#
#1910000
1#
#1920000
0#
#1930000
1#
#1940000
0#
#1950000
1#
#1960000
0#
#1970000
1#
#1980000
0#
#1990000
1#
#2000000
0#
#2010000
1#
#2020000
0#
#2030000
1#
#2040000
0#
#2050000
1#
#2060000
0#
#2070000
1#
#2080000
0#
#2090000
1#
#2100000
0#
#2110000
1#
#2120000
0#
#2130000
1#
#2140000
0#
#2150000
1#
#2160000
0#
#2170000
1#
0$
#2180000
0#
#2190000
1#
#2200000
0#
#2210000
1#
#2220000
0#
#2230000
1#
#2240000
0#
#2250000
1#
#2260000
0#
#2270000
1h
1i
1:
1#
1%
b1 '
b1 (
#2280000
0#
#2290000
0i
b10 g
1#
