ALU_master/divider.v
module divider (
    input [31:0] DD,    // Dividend in IEEE-754
    input [31:0] DS,    // Divisor in IEEE-754
    input control,      // Trigger on positive edge
    input reset,        // Reset process on positive edge
    output reg [31:0] out,      // IEEE-754 formatted result
    output reg exception,       // Exception flag
    output reg zeroDiv          // Zero division flag
);

    // Internal registers
    reg sign;
    reg [7:0] exp_DD, exp_DS, exp_out;
    reg [23:0] mant_DD, mant_DS;
    reg [23:0] quotient;  // Quotient for mantissa division
    integer i;

    // Division function for normalized mantissas
    function [23:0] NRDivisor(
        input [23:0] D1,  // Dividend mantissa
        input [23:0] D2   // Divisor mantissa
    );
        reg [23:0] remainder;
        reg [23:0] temp_quotient;
        reg [23:0] temp_remainder;
        integer i;

        begin
            // Initialize quotient and remainder
            temp_quotient = 0;
            temp_remainder = 0;

            for (i = 23; i >= 0; i = i - 1) begin
                // Shift remainder left and bring down the next bit of dividend
                temp_remainder = (temp_remainder << 1) | D1[i];

                if (temp_remainder >= D2) begin
                    // Subtract divisor from remainder
                    temp_remainder = temp_remainder - D2;
                    // Set the i-th bit of the quotient to 1
                    temp_quotient = temp_quotient | (1 << i);
                end
            end

            // Return the computed quotient
            NRDivisor = temp_quotient;
        end
    endfunction

    // Always block triggered on control or reset signal
    always @(posedge control or posedge reset) begin
        if (reset) begin
            out <= 32'b0;
            exception <= 0;
            zeroDiv <= 0;
        end else begin
            // Step 1: Extract sign, exponent, and mantissa
            sign = DD[31] ^ DS[31];  // XOR for sign bit
            exp_DD = DD[30:23];
            exp_DS = DS[30:23];
            mant_DD = {1'b1, DD[22:0]};  // Add implicit 1 for normalized mantissa
            mant_DS = {1'b1, DS[22:0]};  // Add implicit 1 for normalized mantissa

            // Step 2: Check for divide by zero
            if (DS == 32'b0) begin
                out <= {sign, 8'hFF, 23'b0};  // Infinity
                exception <= 0;
                zeroDiv <= 1;
            end else begin
                zeroDiv <= 0;

                // Step 3: Exponent calculation
                exp_out = exp_DD - exp_DS + 127;  // Adjust bias

                // Step 4: Perform mantissa division
                quotient = NRDivisor(mant_DD, mant_DS);

                // Step 5: Normalize quotient
                while (quotient[23] == 0 && exp_out > 0) begin
                    quotient = quotient << 1;
                    exp_out = exp_out - 1;
                end

                // Step 6: Handle overflow/underflow
                if (exp_out >= 255) begin
                    out <= {sign, 8'hFF, 23'b0};  // Infinity
                    exception <= 1;
                end else if (exp_out <= 0) begin
                    out <= {sign, 8'b0, 23'b0};  // Zero
                    exception <= 1;
                end else begin
                    // Step 7: Remove the leading 1 in normalized mantissa for output
                    out <= {sign, exp_out[7:0], quotient[22:0]};  // Valid result
                    exception <= 0;
                end
            end
        end
    end
endmodule

Multiplyer/multiplier.v
module multiplier (
    input [31:0] A, B,       // IEEE 754 inputs
    input control, reset,     // Control and reset signals
    output reg [31:0] out,    // IEEE 754 result
    output reg exception      // Exception flag
);
    // Internal signals for IEEE 754 decomposition
    reg sign_A, sign_B, sign_out;  // Signs
    reg [7:0] exp_A, exp_B, exp_out;  // Exponents
    reg [23:0] mant_A, mant_B;  // 24-bit mantissas with implied 1
    reg [47:0] product;  // Product from Booth's multiplication

    // Booth’s multiplication logic for mantissas (unsigned)
    function [47:0] booth_multiply(input [23:0] m1, input [23:0] m2);
        reg [47:0] P;  // Partial product
        integer i;
        begin
            P = 0;
            for (i = 0; i < 24; i = i + 1) begin
                if (m2[i])  // If multiplier bit is 1, add shifted multiplicand
                    P = P + (m1 << i);
            end
            booth_multiply = P;  // Return the final product
        end
    endfunction

    // Main logic: IEEE-754 multiplication using Booth’s algorithm
    always @(posedge control or posedge reset) begin
        if (reset) begin
            out <= 32'b0;
            exception <= 0;
        end else begin
            // Step 1: Decompose inputs A and B
            sign_A = A[31];
            sign_B = B[31];
            exp_A = A[30:23];
            exp_B = B[30:23];
            mant_A = {1'b1, A[22:0]};  // Add implied leading 1
            mant_B = {1'b1, B[22:0]};  // Add implied leading 1

            // Step 2: Compute output sign (XOR for signs)
            sign_out = sign_A ^ sign_B;

            // Step 3: Compute exponent
            exp_out = exp_A + exp_B - 127;

            // Step 4: Multiply mantissas using Booth’s algorithm
            product = booth_multiply(mant_A, mant_B);

            // Step 5: Normalize the product (shift if necessary)
            if (product[47]) begin
                out[22:0] = product[46:24];  // Take top 23 bits
                exp_out = exp_out + 1;       // Adjust exponent
            end else begin
                out[22:0] = product[45:23];  // Take top 23 bits
            end
            
            // Step 6: Assemble the IEEE-754 result
            out[31] = sign_out;
            out[30:23] = exp_out;

            // Step 7: Check for exceptions (overflow)
            exception = (exp_out >= 255) ? 1 : 0;
        end
    end
endmodule

Adder_substractor/add_sub.v
module add_sub(
    input [31:0] A, B,         // IEEE 754 input numbers
    input control, reset, addsub, // Control, reset, and add/subtract signals
    output reg [31:0] out,     // IEEE 754 result
    output reg exception       // Exception signal
);
    // Internal signals
    reg [7:0] expA, expB, expOut;     // Exponents
    reg [24:0] mantA, mantB, mantOut; // Mantissas (with leading bits)
    reg signA, signB, signOut;        // Signs
    reg [7:0] expDiff;                // Exponent difference
    reg operation;                    // Actual operation: add (0) / subtract (1)

    // Sequential logic triggered by control or reset
    always @(posedge control or posedge reset) begin
        if (reset) begin
            out <= 32'h00000000;  // Reset the output
            exception <= 0;       // Reset exception flag
        end else begin
            // Step 1: Extract sign, exponent, and mantissa
            signA = A[31];
            
            if (addsub) signB = ~B[31]; // Invert sign of B if subtracting
            else signB = B[31];

            expA = A[30:23];
            expB = B[30:23];
            mantA = {2'b01, A[22:0]}; // Add leading bits to mantissa
            mantB = {2'b01, B[22:0]}; // Add leading bits to mantissa

            // Step 2: Align exponents and mantissas
            if (expA > expB) begin
                expDiff = expA - expB;
                mantB = mantB >> expDiff;
                expOut = expA;
            end else begin
                expDiff = expB - expA;
                mantA = mantA >> expDiff;
                expOut = expB;
            end

            // Step 3: Add or subtract mantissas based on signs
            if (signA == signB) begin
                // If signs are the same, perform addition
                mantOut = mantA + mantB;
                signOut = signA;
            end else begin
                // If signs differ, perform subtraction
                if (mantA >= mantB) begin
                    mantOut = mantA - mantB;
                    signOut = signA;
                end else begin
                    mantOut = mantB - mantA;
                    signOut = signB;
                end
            end

            // Step 4: Normalize the result
            if (mantOut[24]) begin
                mantOut = mantOut >> 1;
                expOut = expOut + 1;
            end else begin
                while (mantOut[23] == 0 && expOut > 0) begin
                    mantOut = mantOut << 1;
                    expOut = expOut - 1;
                end
            end

            // Step 5: Assemble the final IEEE 754 result
            out <= {signOut, expOut, mantOut[22:0]};
            exception <= (expOut == 8'hFF); // Set exception on overflow
        end
    end
endmodule

ALU_master/ALU_top.v
module ALU_top (
    input [31:0] A, B,        // 32-bit IEEE 754 inputs
    input control, reset,     // Control and reset signals
    input [1:0] select,       // Operation select (00: add, 01: sub, 10: mul, 11: div)
    output reg [31:0] out,    // 32-bit IEEE 754 output
    output reg exception,     // General exception signal
    output reg zeroDiv        // Division by zero signal
);
    // Internal signals
    wire [31:0] add_sub_out, mul_out, div_out;
    wire add_sub_exception, mul_exception, div_exception, div_zeroDiv;
    reg addsub_signal;

    // Instantiate add_sub module
    add_sub add_sub_inst (
        .A(A),
        .B(B),
        .control(control),
        .reset(reset),
        .addsub(addsub_signal),
        .out(add_sub_out),
        .exception(add_sub_exception)
    );

    // Instantiate multiplier module
    multiplier mul_inst (
        .A(A),
        .B(B),
        .control(control),
        .reset(reset),
        .out(mul_out),
        .exception(mul_exception)
    );

    // Instantiate divider module
    divider div_inst (
        .DD(A),        // Dividend
        .DS(B),        // Divisor
        .control(control),
        .reset(reset),
        .out(div_out),
        .exception(div_exception),
        .zeroDiv(div_zeroDiv)
    );

    // ALU Operation
    always @(*) begin
        // Initialize outputs
        out = 32'b0;
        exception = 1'b0;
        zeroDiv = 1'b0;

        case (select)
            2'b00: begin // Addition
                addsub_signal = 1'b0; // Set addsub to 0 for addition
                out = add_sub_out;
                exception = add_sub_exception;
            end
            2'b01: begin // Subtraction
                addsub_signal = 1'b1; // Set addsub to 1 for subtraction
                out = add_sub_out;
                exception = add_sub_exception;
            end
            2'b10: begin // Multiplication
                out = mul_out;
                exception = mul_exception;
            end
            2'b11: begin // Division
                out = div_out;
                exception = div_exception;
                zeroDiv = div_zeroDiv;
            end
        endcase
    end

endmodule

ALU_master/ALU_top_tb.v
`timescale 10ns / 1ns
`include "ALU_top.v"
`include "divider.v"
`include "multiplier.v"
`include "add_sub.v"

module ALU_top_tb;
    // Testbench signals
    reg [31:0] A, B;          // Inputs to the ALU
    reg control, reset;       // Control and reset signals
    reg [1:0] select;         // Select signal for operations
    wire [31:0] out;          // Output from the ALU
    wire exception;           // Exception flag
    wire zeroDiv;             // Zero division flag

    // Instantiate the ALU_top module
    ALU_top uut (
        .A(A),
        .B(B),
        .control(control),
        .reset(reset),
        .select(select),
        .out(out),
        .exception(exception),
        .zeroDiv(zeroDiv)
    );

    // Clock generation for control signal (50Hz = 20ms period, or 200,000 clock cycles at 10ns time scale)
    initial begin
        control = 0;
        forever #50 control = ~control;  // Toggle every 100 cycles (1µs per half-cycle at 10ns scale)
    end

    // Test procedure
    initial begin
        $dumpfile("ALU_top_tb.vcd");
        $dumpvars(0, ALU_top_tb);

        // Initialize inputs
        reset = 0;
        A = 32'h00000000;
        B = 32'h00000000;
        select = 2'b00;

        // Reset signal
        #5 reset = 1;
        #5 reset = 0;

        // Test addition (++,+-,-+,--)
        select = 2'b00; // Add
        #100 A = 32'h401762b7; B = 32'h43b69f5c; // 1.0 + 2.0
        #100 A = 32'h401762b7; B = 32'hc3b69f5c; // 1.0 + (-2.0)
        #100 A = 32'hBF800000; B = 32'h40000000; // -1.0 + 2.0
        #100 A = 32'hBF800000; B = 32'hC0000000; // -1.0 + (-2.0)

        // Test subtraction (++,+-,-+,--)
        select = 2'b01; // Sub
        #100 A = 32'h3F800000; B = 32'h40000000; // 1.0 - 2.0
        #100 A = 32'h3F800000; B = 32'hC0000000; // 1.0 - (-2.0)
        #100 A = 32'hBF800000; B = 32'h40000000; // -1.0 - 2.0
        #100 A = 32'hBF800000; B = 32'hC0000000; // -1.0 - (-2.0)

        // Test multiplication (++,+-,-+,--)
        select = 2'b10; // Mul
        #100 A = 32'h3F800000; B = 32'h40000000; // 1.0 * 2.0
        #100 A = 32'h3F800000; B = 32'hC0000000; // 1.0 * (-2.0)
        #100 A = 32'hBF800000; B = 32'h40000000; // -1.0 * 2.0
        #100 A = 32'hBF800000; B = 32'hC0000000; // -1.0 * (-2.0)

        // Test division (++,+-,-+,--)
        select = 2'b11; // Div
        #100 A = 32'h3F800000; B = 32'h40000000; // 1.0 / 2.0
        #100 A = 32'h3F800000; B = 32'hC0000000; // 1.0 / (-2.0)
        #100 A = 32'hBF800000; B = 32'h40000000; // -1.0 / 2.0
        #100 A = 32'hBF800000; B = 32'hC0000000; // -1.0 / (-2.0)

        // Test exception cases
        #100 A = 32'h7F800000; B = 32'h7F800000; // Inf + Inf (exception expected)
        
        // Test zero division
        #100 A = 32'h3F800000; B = 32'h00000000; // 1.0 / 0.0 (zero division expected)

        #200 $finish; // End simulation
    end

    // Monitor outputs
initial begin
    // Monitor the signals at every positive edge of the control signal
    forever @(posedge control) begin
        #10
        $display("%0t %b %h %h %h %b %b", 
                 $time, select, A, B, out, exception, zeroDiv);
    end
end

endmodule

ALU_master/ALU_top_tb.vcd
$date
	Sun Dec 08 20:35:05 2024
$end
$version
	Icarus Verilog
$end
$timescale
	1ns
$end
$scope module ALU_top_tb $end
$var wire 1 ! zeroDiv $end
$var wire 32 " out [31:0] $end
$var wire 1 # exception $end
$var reg 32 $ A [31:0] $end
$var reg 32 % B [31:0] $end
$var reg 1 & control $end
$var reg 1 ' reset $end
$var reg 2 ( select [1:0] $end
$scope module uut $end
$var wire 32 ) A [31:0] $end
$var wire 32 * B [31:0] $end
$var wire 1 & control $end
$var wire 1 ' reset $end
$var wire 2 + select [1:0] $end
$var wire 32 , mul_out [31:0] $end
$var wire 1 - mul_exception $end
$var wire 1 . div_zeroDiv $end
$var wire 32 / div_out [31:0] $end
$var wire 1 0 div_exception $end
$var wire 32 1 add_sub_out [31:0] $end
$var wire 1 2 add_sub_exception $end
$var reg 1 3 addsub_signal $end
$var reg 1 # exception $end
$var reg 32 4 out [31:0] $end
$var reg 1 ! zeroDiv $end
$scope module add_sub_inst $end
$var wire 32 5 A [31:0] $end
$var wire 32 6 B [31:0] $end
$var wire 1 3 addsub $end
$var wire 1 & control $end
$var wire 1 ' reset $end
$var reg 1 2 exception $end
$var reg 8 7 expA [7:0] $end
$var reg 8 8 expB [7:0] $end
$var reg 8 9 expDiff [7:0] $end
$var reg 8 : expOut [7:0] $end
$var reg 25 ; mantA [24:0] $end
$var reg 25 < mantB [24:0] $end
$var reg 25 = mantOut [24:0] $end
$var reg 32 > out [31:0] $end
$var reg 1 ? signA $end
$var reg 1 @ signB $end
$var reg 1 A signOut $end
$upscope $end
$scope module div_inst $end
$var wire 32 B DD [31:0] $end
$var wire 32 C DS [31:0] $end
$var wire 1 & control $end
$var wire 1 ' reset $end
$var reg 1 0 exception $end
$var reg 8 D exp_DD [7:0] $end
$var reg 8 E exp_DS [7:0] $end
$var reg 8 F exp_out [7:0] $end
$var reg 24 G mant_DD [23:0] $end
$var reg 24 H mant_DS [23:0] $end
$var reg 32 I out [31:0] $end
$var reg 24 J quotient [23:0] $end
$var reg 1 K sign $end
$var reg 1 . zeroDiv $end
$scope function NRDivisor $end
$var reg 24 L D1 [23:0] $end
$var reg 24 M D2 [23:0] $end
$var reg 24 N temp_quotient [23:0] $end
$var reg 24 O temp_remainder [23:0] $end
$var integer 32 P i [31:0] $end
$upscope $end
$upscope $end
$scope module mul_inst $end
$var wire 32 Q A [31:0] $end
$var wire 32 R B [31:0] $end
$var wire 1 & control $end
$var wire 1 ' reset $end
$var reg 1 - exception $end
$var reg 8 S exp_A [7:0] $end
$var reg 8 T exp_B [7:0] $end
$var reg 8 U exp_out [7:0] $end
$var reg 24 V mant_A [23:0] $end
$var reg 24 W mant_B [23:0] $end
$var reg 32 X out [31:0] $end
$var reg 48 Y product [47:0] $end
$var reg 1 Z sign_A $end
$var reg 1 [ sign_B $end
$var reg 1 \ sign_out $end
$scope function booth_multiply $end
$var reg 48 ] P [47:0] $end
$var reg 24 ^ m1 [23:0] $end
$var reg 24 _ m2 [23:0] $end
$var integer 32 ` i [31:0] $end
$upscope $end
$upscope $end
$upscope $end
$upscope $end
$enddefinitions $end
$comment Show the parameter values. $end
$dumpall
$end
#0
$dumpvars
bx `
bx _
bx ^
bx ]
x\
x[
xZ
bx Y
bx X
bx W
bx V
bx U
bx T
bx S
b0 R
b0 Q
bx P
bx O
bx N
bx M
bx L
xK
bx J
bx I
bx H
bx G
bx F
bx E
bx D
b0 C
b0 B
xA
x@
x?
bx >
bx =
bx <
bx ;
bx :
bx 9
bx 8
bx 7
b0 6
b0 5
bx 4
03
x2
bx 1
x0
bx /
x.
x-
bx ,
b0 +
b0 *
b0 )
b0 (
0'
0&
b0 %
b0 $
x#
bx "
0!
$end
#50
0#
b0 "
b0 4
02
b0 1
b0 >
0-
b0 ,
b0 X
0.
00
b0 /
b0 I
1'
#100
0'
#500
b100000000000000000000000 "
b100000000000000000000000 4
1.
b1111111100000000000000000000000 /
b1111111100000000000000000000000 I
b100000000000000000000000 1
b100000000000000000000000 >
b100000000000000000000000 H
b100000000000000000000000 G
b0 E
b0 D
0K
b1000000100000000000000000000000 ,
b1000000100000000000000000000000 X
b10000000000000000000000000000000000000000000000 Y
b11000 `
b10000000000000000000000000000000000000000000000 ]
b100000000000000000000000 ^
b100000000000000000000000 _
b10000001 U
0\
b100000000000000000000000 W
b100000000000000000000000 V
b0 T
b0 S
0[
0Z
0A
b100000000000000000000000 =
b1 :
b0 9
b100000000000000000000000 <
b100000000000000000000000 ;
b0 8
b0 7
0@
0?
1&
#1000
0&
#1100
b1000011101101101001111101011100 %
b1000011101101101001111101011100 *
b1000011101101101001111101011100 6
b1000011101101101001111101011100 C
b1000011101101101001111101011100 R
b1000000000101110110001010110111 $
b1000000000101110110001010110111 )
b1000000000101110110001010110111 5
b1000000000101110110001010110111 B
b1000000000101110110001010110111 Q
#1500
b1000011101101111100111000100001 1
b1000011101101111100111000100001 >
10
b0 /
b0 I
0.
b1000011101101111100111000100001 "
b1000011101101111100111000100001 4
b101101111100111000100001 =
b10000111 :
b111 9
b101101101001111101011100 <
b10010111011000101 ;
b10000111 8
b10000000 7
b1000100010101111111110011010101 ,
b1000100010101111111110011010101 X
b11010111111111001101010110100010010001011000100 Y
b11000 `
b11010111111111001101010110100010010001011000100 ]
b100101110110001010110111 ^
b101101101001111101011100 _
b10001000 U
b101101101001111101011100 W
b100101110110001010110111 V
b10000111 T
b10000000 S
b0 J
b11111111111111111111111111111111 P
b100101110110001010110111 O
b0 N
b100101110110001010110111 L
b101101101001111101011100 M
b0 F
b101101101001111101011100 H
b100101110110001010110111 G
b10000111 E
b10000000 D
1&
#2000
0&
#2100
b11000011101101101001111101011100 %
b11000011101101101001111101011100 *
b11000011101101101001111101011100 6
b11000011101101101001111101011100 C
b11000011101101101001111101011100 R
#2500
b10000000000000000000000000000000 /
b10000000000000000000000000000000 I
b11000011101101010111000010010111 1
b11000011101101010111000010010111 >
b11000011101101010111000010010111 "
b11000011101101010111000010010111 4
b11111111111111111111111111111111 P
b100101110110001010110111 O
b0 F
1K
b11000100010101111111110011010101 ,
b11000100010101111111110011010101 X
b11000 `
b11010111111111001101010110100010010001011000100 ]
1\
1[
1A
b101101010111000010010111 =
b10010111011000101 ;
1@
1&
#3000
0&
#3100
b1000000000000000000000000000000 %
b1000000000000000000000000000000 *
b1000000000000000000000000000000 6
b1000000000000000000000000000000 C
b1000000000000000000000000000000 R
b10111111100000000000000000000000 $
b10111111100000000000000000000000 )
b10111111100000000000000000000000 5
b10111111100000000000000000000000 B
b10111111100000000000000000000000 Q
#3500
b111111100000000000000000000000 1
b111111100000000000000000000000 >
00
b10110011100000000000000000000000 /
b10110011100000000000000000000000 I
b111111100000000000000000000000 "
b111111100000000000000000000000 4
0A
b100000000000000000000000 =
b1111111 :
b1 9
b100000000000000000000000 <
b10000000000000000000000 ;
b10000000 8
b1111111 7
0@
1?
b11000000000000000000000000000000 ,
b11000000000000000000000000000000 X
b10000000000000000000000000000000000000000000000 Y
b11000 `
b10000000000000000000000000000000000000000000000 ]
b100000000000000000000000 ^
b100000000000000000000000 _
b10000000 U
b100000000000000000000000 W
b100000000000000000000000 V
b10000000 T
b1111111 S
0[
1Z
b100000000000000000000000 J
b1 N
b11111111111111111111111111111111 P
b0 O
b100000000000000000000000 L
b100000000000000000000000 M
b1100111 F
b100000000000000000000000 H
b100000000000000000000000 G
b10000000 E
b1111111 D
1&
#4000
0&
#4100
13
b111111100000000000000000000000 "
b111111100000000000000000000000 4
b1 (
b1 +
b11000000000000000000000000000000 %
b11000000000000000000000000000000 *
b11000000000000000000000000000000 6
b11000000000000000000000000000000 C
b11000000000000000000000000000000 R
#4500
b110011100000000000000000000000 /
b110011100000000000000000000000 I
b111111100000000000000000000000 "
b111111100000000000000000000000 4
b100000000000000000000000 J
b0 O
b11111111111111111111111111111111 P
b1 N
b1100111 F
0K
b1000000000000000000000000000000 ,
b1000000000000000000000000000000 X
b11000 `
b10000000000000000000000000000000000000000000000 ]
0\
1[
b100000000000000000000000 =
b1111111 :
b10000000000000000000000 ;
1&
#5000
0&
#5100
b1000000000000000000000000000000 %
b1000000000000000000000000000000 *
b1000000000000000000000000000000 6
b1000000000000000000000000000000 C
b1000000000000000000000000000000 R
b111111100000000000000000000000 $
b111111100000000000000000000000 )
b111111100000000000000000000000 5
b111111100000000000000000000000 B
b111111100000000000000000000000 Q
#5500
b10111111100000000000000000000000 "
b10111111100000000000000000000000 4
b10111111100000000000000000000000 1
b10111111100000000000000000000000 >
1A
b100000000000000000000000 =
b1111111 :
b10000000000000000000000 ;
1@
0?
b11000 `
b10000000000000000000000000000000000000000000000 ]
0[
0Z
b100000000000000000000000 J
b0 O
b11111111111111111111111111111111 P
b1 N
b1100111 F
1&
#6000
0&
#6100
b11000000000000000000000000000000 %
b11000000000000000000000000000000 *
b11000000000000000000000000000000 6
b11000000000000000000000000000000 C
b11000000000000000000000000000000 R
#6500
b10110011100000000000000000000000 /
b10110011100000000000000000000000 I
b1000000010000000000000000000000 1
b1000000010000000000000000000000 >
b1000000010000000000000000000000 "
b1000000010000000000000000000000 4
b100000000000000000000000 J
b0 O
b11111111111111111111111111111111 P
b1 N
b1100111 F
1K
b11000000000000000000000000000000 ,
b11000000000000000000000000000000 X
b11000 `
b10000000000000000000000000000000000000000000000 ]
1\
1[
0A
b110000000000000000000000 =
b10000000 :
b10000000000000000000000 ;
0@
1&
#7000
0&
#7100
b1000000000000000000000000000000 %
b1000000000000000000000000000000 *
b1000000000000000000000000000000 6
b1000000000000000000000000000000 C
b1000000000000000000000000000000 R
b10111111100000000000000000000000 $
b10111111100000000000000000000000 )
b10111111100000000000000000000000 5
b10111111100000000000000000000000 B
b10111111100000000000000000000000 Q
#7500
b11000000010000000000000000000000 "
b11000000010000000000000000000000 4
b11000000010000000000000000000000 1
b11000000010000000000000000000000 >
1A
b10000000000000000000000 ;
1@
1?
b11000 `
b10000000000000000000000000000000000000000000000 ]
0[
1Z
b100000000000000000000000 J
b0 O
b11111111111111111111111111111111 P
b1 N
b1100111 F
1&
#8000
0&
#8100
b11000000000000000000000000000000 "
b11000000000000000000000000000000 4
b10 (
b10 +
b11000000000000000000000000000000 %
b11000000000000000000000000000000 *
b11000000000000000000000000000000 6
b11000000000000000000000000000000 C
b11000000000000000000000000000000 R
#8500
b110011100000000000000000000000 /
b110011100000000000000000000000 I
b111111100000000000000000000000 1
b111111100000000000000000000000 >
b1000000000000000000000000000000 "
b1000000000000000000000000000000 4
b100000000000000000000000 J
b0 O
b11111111111111111111111111111111 P
b1 N
b1100111 F
0K
b1000000000000000000000000000000 ,
b1000000000000000000000000000000 X
b11000 `
b10000000000000000000000000000000000000000000000 ]
0\
1[
b1111111 :
0A
b100000000000000000000000 =
b10000000000000000000000 ;
0@
1&
#9000
0&
#9100
b1000000000000000000000000000000 %
b1000000000000000000000000000000 *
b1000000000000000000000000000000 6
b1000000000000000000000000000000 C
b1000000000000000000000000000000 R
b111111100000000000000000000000 $
b111111100000000000000000000000 )
b111111100000000000000000000000 5
b111111100000000000000000000000 B
b111111100000000000000000000000 Q
#9500
b1000000000000000000000000000000 "
b1000000000000000000000000000000 4
b10111111100000000000000000000000 1
b10111111100000000000000000000000 >
1A
b100000000000000000000000 =
b1111111 :
b10000000000000000000000 ;
1@
0?
b11000 `
b10000000000000000000000000000000000000000000000 ]
0[
0Z
b100000000000000000000000 J
b0 O
b11111111111111111111111111111111 P
b1 N
b1100111 F
1&
#10000
0&
#10100
b11000000000000000000000000000000 %
b11000000000000000000000000000000 *
b11000000000000000000000000000000 6
b11000000000000000000000000000000 C
b11000000000000000000000000000000 R
#10500
b10110011100000000000000000000000 /
b10110011100000000000000000000000 I
b1000000010000000000000000000000 1
b1000000010000000000000000000000 >
b11000000000000000000000000000000 "
b11000000000000000000000000000000 4
b100000000000000000000000 J
b0 O
b11111111111111111111111111111111 P
b1 N
b1100111 F
1K
b11000000000000000000000000000000 ,
b11000000000000000000000000000000 X
b11000 `
b10000000000000000000000000000000000000000000000 ]
1\
1[
0A
b110000000000000000000000 =
b10000000 :
b10000000000000000000000 ;
0@
1&
#11000
0&
#11100
b1000000000000000000000000000000 %
b1000000000000000000000000000000 *
b1000000000000000000000000000000 6
b1000000000000000000000000000000 C
b1000000000000000000000000000000 R
b10111111100000000000000000000000 $
b10111111100000000000000000000000 )
b10111111100000000000000000000000 5
b10111111100000000000000000000000 B
b10111111100000000000000000000000 Q
#11500
b11000000000000000000000000000000 "
b11000000000000000000000000000000 4
b11000000010000000000000000000000 1
b11000000010000000000000000000000 >
1A
b10000000000000000000000 ;
1@
1?
b11000 `
b10000000000000000000000000000000000000000000000 ]
0[
1Z
b100000000000000000000000 J
b0 O
b11111111111111111111111111111111 P
b1 N
b1100111 F
1&
#12000
0&
#12100
b10110011100000000000000000000000 "
b10110011100000000000000000000000 4
b11 (
b11 +
b11000000000000000000000000000000 %
b11000000000000000000000000000000 *
b11000000000000000000000000000000 6
b11000000000000000000000000000000 C
b11000000000000000000000000000000 R
#12500
b110011100000000000000000000000 /
b110011100000000000000000000000 I
b111111100000000000000000000000 1
b111111100000000000000000000000 >
b110011100000000000000000000000 "
b110011100000000000000000000000 4
b100000000000000000000000 J
b0 O
b11111111111111111111111111111111 P
b1 N
b1100111 F
0K
b1000000000000000000000000000000 ,
b1000000000000000000000000000000 X
b11000 `
b10000000000000000000000000000000000000000000000 ]
0\
1[
b1111111 :
0A
b100000000000000000000000 =
b10000000000000000000000 ;
0@
1&
#13000
0&
#13100
b1000000000000000000000000000000 %
b1000000000000000000000000000000 *
b1000000000000000000000000000000 6
b1000000000000000000000000000000 C
b1000000000000000000000000000000 R
b111111100000000000000000000000 $
b111111100000000000000000000000 )
b111111100000000000000000000000 5
b111111100000000000000000000000 B
b111111100000000000000000000000 Q
#13500
b110011100000000000000000000000 "
b110011100000000000000000000000 4
b10111111100000000000000000000000 1
b10111111100000000000000000000000 >
1A
b100000000000000000000000 =
b1111111 :
b10000000000000000000000 ;
1@
0?
b11000 `
b10000000000000000000000000000000000000000000000 ]
0[
0Z
b100000000000000000000000 J
b0 O
b11111111111111111111111111111111 P
b1 N
b1100111 F
1&
#14000
0&
#14100
b11000000000000000000000000000000 %
b11000000000000000000000000000000 *
b11000000000000000000000000000000 6
b11000000000000000000000000000000 C
b11000000000000000000000000000000 R
#14500
b10110011100000000000000000000000 /
b10110011100000000000000000000000 I
b1000000010000000000000000000000 1
b1000000010000000000000000000000 >
b10110011100000000000000000000000 "
b10110011100000000000000000000000 4
b100000000000000000000000 J
b0 O
b11111111111111111111111111111111 P
b1 N
b1100111 F
1K
b11000000000000000000000000000000 ,
b11000000000000000000000000000000 X
b11000 `
b10000000000000000000000000000000000000000000000 ]
1\
1[
0A
b110000000000000000000000 =
b10000000 :
b10000000000000000000000 ;
0@
1&
#15000
0&
#15100
b1000000000000000000000000000000 %
b1000000000000000000000000000000 *
b1000000000000000000000000000000 6
b1000000000000000000000000000000 C
b1000000000000000000000000000000 R
b10111111100000000000000000000000 $
b10111111100000000000000000000000 )
b10111111100000000000000000000000 5
b10111111100000000000000000000000 B
b10111111100000000000000000000000 Q
#15500
b10110011100000000000000000000000 "
b10110011100000000000000000000000 4
b11000000010000000000000000000000 1
b11000000010000000000000000000000 >
1A
b10000000000000000000000 ;
1@
1?
b11000 `
b10000000000000000000000000000000000000000000000 ]
0[
1Z
b100000000000000000000000 J
b0 O
b11111111111111111111111111111111 P
b1 N
b1100111 F
1&
#16000
0&
#16100
b11000000000000000000000000000000 %
b11000000000000000000000000000000 *
b11000000000000000000000000000000 6
b11000000000000000000000000000000 C
b11000000000000000000000000000000 R
#16500
b110011100000000000000000000000 /
b110011100000000000000000000000 I
b111111100000000000000000000000 1
b111111100000000000000000000000 >
b110011100000000000000000000000 "
b110011100000000000000000000000 4
b100000000000000000000000 J
b0 O
b11111111111111111111111111111111 P
b1 N
b1100111 F
0K
b1000000000000000000000000000000 ,
b1000000000000000000000000000000 X
b11000 `
b10000000000000000000000000000000000000000000000 ]
0\
1[
b1111111 :
0A
b100000000000000000000000 =
b10000000000000000000000 ;
0@
1&
#17000
0&
#17100
b1111111100000000000000000000000 %
b1111111100000000000000000000000 *
b1111111100000000000000000000000 6
b1111111100000000000000000000000 C
b1111111100000000000000000000000 R
b1111111100000000000000000000000 $
b1111111100000000000000000000000 )
b1111111100000000000000000000000 5
b1111111100000000000000000000000 B
b1111111100000000000000000000000 Q
#17500
b0 1
b0 >
b110100000000000000000000000000 /
b110100000000000000000000000000 I
b110100000000000000000000000000 "
b110100000000000000000000000000 4
b0 =
b0 :
b0 9
b100000000000000000000000 ;
b11111111 8
b11111111 7
1@
0?
b111111100000000000000000000000 ,
b111111100000000000000000000000 X
b11000 `
b10000000000000000000000000000000000000000000000 ]
b1111111 U
b11111111 T
b11111111 S
0[
0Z
b100000000000000000000000 J
b0 O
b11111111111111111111111111111111 P
b1 N
b1101000 F
b11111111 E
b11111111 D
1&
#18000
0&
#18100
b0 %
b0 *
b0 6
b0 C
b0 R
b111111100000000000000000000000 $
b111111100000000000000000000000 )
b111111100000000000000000000000 5
b111111100000000000000000000000 B
b111111100000000000000000000000 Q
#18500
1!
1.
b1111111100000000000000000000000 /
b1111111100000000000000000000000 I
b111111100000000000000000000000 1
b111111100000000000000000000000 >
b1111111100000000000000000000000 "
b1111111100000000000000000000000 4
b0 E
b1111111 D
b0 ,
b0 X
b11000 `
b10000000000000000000000000000000000000000000000 ]
b0 U
b0 T
b1111111 S
b100000000000000000000000 =
b1111111 :
b0 <
b1111111 9
b0 8
b1111111 7
1&
#19000
0&
#19500
b0 <
b11000 `
b10000000000000000000000000000000000000000000000 ]
1&
#20000
0&
