Divider/divider.v
module divider (
    input [31:0] DD,   // Dividend in IEEE-754
    input [31:0] DS,   // Divisor in IEEE-754
    input control,     // Trigger on positive edge
    input reset,       // Reset process on positive edge
    output reg [31:0] out,    // IEEE-754 formatted result
    output reg exception,     // Exception flag
    output reg zeroDiv        // Zero division flag
);

    // Internal registers
    reg sign;
    reg [7:0] exp_DD, exp_DS, exp_out;
    reg [23:0] mant_DD, mant_DS;
    reg [47:0] remainder;  // Remainder register for division
    reg [23:0] quotient;   // Quotient for mantissa division
    integer i;

    always @(posedge control or posedge reset) begin
        if (reset) begin
            out <= 32'b0;
            exception <= 0;
            zeroDiv <= 0;
        end else begin
            // Step 1: Extract sign, exponent, and mantissa
            sign = DD[31] ^ DS[31];  // XOR for sign bit
            exp_DD = DD[30:23];
            exp_DS = DS[30:23];
            mant_DD = {1'b1, DD[22:0]};  // Add implicit 1
            mant_DS = {1'b1, DS[22:0]};  // Add implicit 1

            // Step 2: Check for divide by zero
            if (DS == 32'b0) begin
                out <= {sign, 8'hFF, 23'b0};  // Infinity
                exception <= 0;
                zeroDiv <= 1;
                // Stop further processing
            end

            // Step 3: Exponent calculation
            exp_out = exp_DD - exp_DS + 127;  // Bias adjustment

            // Step 4: Initialize remainder and quotient
            remainder = mant_DD << 24;  // Align dividend
            quotient = 0;

            // Step 5: SRT Division Algorithm
            for (i = 0; i < 24; i = i + 1) begin
                remainder = remainder << 1;  // Shift left
                if (remainder[47:24] >= mant_DS) begin
                    remainder[47:24] = remainder[47:24] - mant_DS;
                    quotient = (quotient << 1) | 1;  // Set LSB to 1
                end else begin
                    quotient = quotient << 1;  // Set LSB to 0
                end
            end

            // Step 6: Normalize quotient
            if (quotient[23] == 0) begin
                quotient = quotient << 1;
                exp_out = exp_out - 1;
            end

            // Step 7: Handle overflow/underflow
            if (exp_out >= 255) begin
                out <= {sign, 8'hFF, 23'b0};  // Infinity
                exception <= 1;
            end else if (exp_out <= 0) begin
                out <= {sign, 8'b0, 23'b0};  // Zero
                exception <= 1;
            end else begin
                out <= {sign, exp_out[7:0], quotient[22:0]};  // Valid result
                exception <= 0;
            end
        end
    end
endmodule

Divider/divider_tb.v
`timescale 10ns / 1ns
`include "divider.v"

module divider_tb;
    // Testbench signals
    reg [31:0] DD;          // Dividend in IEEE-754
    reg [31:0] DS;          // Divisor in IEEE-754
    reg control;            // Control signal
    reg reset;              // Reset signal
    wire [31:0] out;       // Output from the divider
    wire exception;        // Exception signal
    wire zeroDiv;         // Zero division flag

    // Instantiate the divider module
    divider uut (
        .DD(DD),
        .DS(DS),
        .control(control),
        .reset(reset),
        .out(out),
        .exception(exception),
        .zeroDiv(zeroDiv)
    );

    // Clock generation for control signal
    initial begin
        control = 0;
        forever #10 control = ~control;  // Toggle every 10ns
    end

    // Test procedure
    initial begin
        $dumpfile("divider_tb.vcd");
        $dumpvars(0, divider_tb);

        // Initialize inputs
        reset = 0;
        DD = 32'h00000000;  // Initially zero
        DS = 32'h00000000;  // Initially zero

        // Test Case 1: Division of 4.5 by 1.5
        #5 reset = 1;  // Assert reset
        #5 reset = 0;  // De-assert reset
        DD = 32'h40900000; // 4.5 in IEEE-754
        DS = 32'h3FC00000; // 1.5 in IEEE-754
        #20;  // Wait for output to settle
        #5;  // Allow for next control pulse

        // Test Case 2: Division of 6.0 by 3.0
        DD = 32'h40C00000; // 6.0 in IEEE-754
        DS = 32'h40400000; // 3.0 in IEEE-754
        #20;  // Wait for output to settle
        #5;  // Allow for next control pulse

        // Test Case 3: Division of 3.0 by 0.0 (should handle divide by zero)
        DD = 32'h40400000; // 3.0 in IEEE-754
        DS = 32'h00000000; // 0.0 in IEEE-754
        #20;  // Wait for output to settle
        #5;  // Allow for next control pulse

        // Test Case 4: Division of 0.0 by 3.0 (should return 0)
        DD = 32'h00000000; // 0.0 in IEEE-754
        DS = 32'h40400000; // 3.0 in IEEE-754
        #20;  // Wait for output to settle
        #5;  // Allow for next control pulse

        // Test Case 5: Division of -4.5 by 1.5
        DD = 32'hC0900000; // -4.5 in IEEE-754
        DS = 32'h3FC00000; // 1.5 in IEEE-754
        #20;  // Wait for output to settle
        #5;  // Allow for next control pulse

        // Test Case 6: Division of -6.0 by 0.0 (should handle divide by zero)
        DD = 32'hC0C00000; // -6.0 in IEEE-754
        DS = 32'h00000000; // 0.0 in IEEE-754
        #20;  // Wait for output to settle
        #5;  // Allow for next control pulse

        // Test Case 7: Division of 0.0 by -3.0 (should return 0)
        DD = 32'h00000000; // 0.0 in IEEE-754
        DS = 32'hC0400000; // -3.0 in IEEE-754
        #20;  // Wait for output to settle
        #5;  // Allow for next control pulse

        // End the simulation
        #5 $finish;
    end

    // Monitor output and exceptions
    initial begin
        $monitor("Time: %0t | DD: %h | DS: %h | Out: %h | Exception: %b | ZeroDiv: %b",
                 $time, DD, DS, out, exception, zeroDiv);
    end
endmodule

Divider/divider_tb.vcd
$date
	Sat Oct 19 01:11:40 2024
$end
$version
	Icarus Verilog
$end
$timescale
	1ns
$end
$scope module divider_tb $end
$var wire 1 ! zeroDiv $end
$var wire 32 " out [31:0] $end
$var wire 1 # exception $end
$var reg 32 $ DD [31:0] $end
$var reg 32 % DS [31:0] $end
$var reg 1 & control $end
$var reg 1 ' reset $end
$scope module uut $end
$var wire 32 ( DD [31:0] $end
$var wire 32 ) DS [31:0] $end
$var wire 1 & control $end
$var wire 1 ' reset $end
$var reg 1 # exception $end
$var reg 8 * exp_DD [7:0] $end
$var reg 8 + exp_DS [7:0] $end
$var reg 8 , exp_out [7:0] $end
$var reg 24 - mant_DD [23:0] $end
$var reg 24 . mant_DS [23:0] $end
$var reg 32 / out [31:0] $end
$var reg 24 0 quotient [23:0] $end
$var reg 48 1 remainder [47:0] $end
$var reg 1 2 sign $end
$var reg 1 ! zeroDiv $end
$var integer 32 3 i [31:0] $end
$upscope $end
$upscope $end
$enddefinitions $end
$comment Show the parameter values. $end
$dumpall
$end
#0
$dumpvars
bx 3
x2
bx 1
bx 0
bx /
bx .
bx -
bx ,
bx +
bx *
b0 )
b0 (
0'
0&
b0 %
b0 $
x#
bx "
x!
$end
#50
0!
0#
b0 "
b0 /
1'
#100
b1000000000000000000000000000000 "
b1000000000000000000000000000000 /
b11000 3
b0 0
b0 1
b10000000 ,
b110000000000000000000000 .
b100100000000000000000000 -
b1111111 +
b10000001 *
02
b111111110000000000000000000000 %
b111111110000000000000000000000 )
b1000000100100000000000000000000 $
b1000000100100000000000000000000 (
0'
1&
#200
0&
#300
b11000 3
b0 1
b10000000 ,
1&
#350
b1000000010000000000000000000000 %
b1000000010000000000000000000000 )
b1000000110000000000000000000000 $
b1000000110000000000000000000000 (
#400
0&
#500
b111111100000000000000000000000 "
b111111100000000000000000000000 /
b1111111 ,
b11000 3
b0 1
b110000000000000000000000 -
b10000000 +
1&
#600
b0 %
b0 )
b1000000010000000000000000000000 $
b1000000010000000000000000000000 (
0&
#700
1#
1!
b1111111100000000000000000000000 "
b1111111100000000000000000000000 /
b100000000000000000000000 0
b11000 3
b0 1
b11111111 ,
b100000000000000000000000 .
b0 +
b10000000 *
1&
#800
0&
#850
b1000000010000000000000000000000 %
b1000000010000000000000000000000 )
b0 $
b0 (
#900
0#
b1111111000000000000000000000000 "
b1111111000000000000000000000000 /
b11111110 ,
b11000 3
b0 0
b0 1
b110000000000000000000000 .
b100000000000000000000000 -
b10000000 +
b0 *
1&
#1000
0&
#1100
b11000000000000000000000000000000 "
b11000000000000000000000000000000 /
b11000 3
b0 1
b10000000 ,
b100100000000000000000000 -
b1111111 +
b10000001 *
12
b111111110000000000000000000000 %
b111111110000000000000000000000 )
b11000000100100000000000000000000 $
b11000000100100000000000000000000 (
1&
#1200
0&
#1300
b11000 3
b0 1
b10000000 ,
1&
#1350
b0 %
b0 )
b11000000110000000000000000000000 $
b11000000110000000000000000000000 (
#1400
0&
#1500
1#
b10000000000000000000000000000000 "
b10000000000000000000000000000000 /
b100000000000000000000000 0
b11000 3
b0 1
b0 ,
b100000000000000000000000 .
b110000000000000000000000 -
b0 +
1&
#1600
b11000000010000000000000000000000 %
b11000000010000000000000000000000 )
b0 $
b0 (
0&
#1700
0#
b11111111000000000000000000000000 "
b11111111000000000000000000000000 /
b11000 3
b0 0
b0 1
b11111110 ,
b110000000000000000000000 .
b100000000000000000000000 -
b10000000 +
b0 *
1&
#1800
0&
#1900
b11000 3
b0 1
b11111110 ,
1&
