Memory/memory.v
module memory (
    input clk,                // Clock signal
    input dataready,          // Signal to start data sending
    input stop,               // Signal to stop data temporarily
    output reg num1_bit,      // Bitwise output of num1 (IEEE 754 floating point)
    output reg num2_bit,      // Bitwise output of num2 (IEEE 754 floating point)
    output reg select0,       // First bit of selection signal output
    output reg select1,       // Second bit of selection signal output
    output reg ok             // Output signal to indicate data sending completion
);

    // Four data sets
    reg [31:0] num1_data [3:0]; // Array of num1 values
    reg [31:0] num2_data [3:0]; // Array of num2 values
    reg [1:0] select_data [3:0]; // Array of select values
    
    reg [1:0] data_index;    // Index to track which data set is being sent
    reg [5:0] bit_index;     // Index to track which bit is being sent (0 to 31)

    // State machine states
    reg [1:0] state;  
    localparam IDLE = 2'b00, SEND_DATA = 2'b01, WAIT_STOP = 2'b10;

    // Initialization of data sets
    initial begin
        num1_data[0] = 32'h4048F5C3;  // 3.14 in IEEE 754
        num2_data[0] = 32'h41AD0651;  // 21.654 in IEEE 754
        select_data[0] = 2'b00;
        
        num1_data[1] = 32'hC0490FDB;  // -3.14 in IEEE 754
        num2_data[1] = 32'h41B2C8EC;  // 22.45 in IEEE 754
        select_data[1] = 2'b01;
        
        num1_data[2] = 32'h40C90FDB;  // 6.28318 (2 * pi) in IEEE 754
        num2_data[2] = 32'h41200000;  // 10.0 in IEEE 754
        select_data[2] = 2'b10;
        
        num1_data[3] = 32'hC1200000;  // -10.0 in IEEE 754
        num2_data[3] = 32'h412C0000;  // 10.75 in IEEE 754
        select_data[3] = 2'b11;
        
        // Initialize other signals
        data_index = 0;
        bit_index = 0;
        num1_bit = 0;
        num2_bit = 0;
        select0 = 0;
        select1 = 0;
        ok = 0;
        state = IDLE;
    end

    always @(posedge clk) begin
        case (state)
            IDLE: begin
                if (dataready == 1'b1) begin
                    // Start sending data when dataready goes high
                    bit_index <= 31;  // Start with MSB
                    select0 <= select_data[data_index][0];
                    select1 <= select_data[data_index][1];
                    ok <= 1'b0;  // Clear ok signal
                    state <= SEND_DATA;
                end
            end

            SEND_DATA: begin
                if (!stop) begin
                    // Send bits of num1 and num2 one by one
                    num1_bit <= num1_data[data_index][bit_index];  // Send MSB first
                    num2_bit <= num2_data[data_index][bit_index];  // Send MSB first
                    
                    if (bit_index > 0) begin
                        bit_index <= bit_index - 1;
                    end else begin
                        // After all 32 bits are sent, signal completion
                        ok <= 1'b1;
                        state <= WAIT_STOP;
                    end
                end
            end

            WAIT_STOP: begin
                if (stop == 1'b1) begin
                    // Stop the process temporarily
                    ok <= 1'b0;      // Clear ok
                    num1_bit <= 1'b0; // Clear num1 bit
                    num2_bit <= 1'b0; // Clear num2 bit
                    select0 <= 1'b0;  // Clear select0
                    select1 <= 1'b0;  // Clear select1

                    // Move to the next data set
                    if (data_index < 3) begin
                        data_index <= data_index + 1;
                    end else begin
                        data_index <= 0; // Loop back to the first data set
                    end
                    state <= IDLE;  // Go back to idle state
                end
            end
        endcase
    end
endmodule

Memory/memory_tb.v
`timescale 1ns/1ps
`include "memory.v"

module memory_tb;
    reg clk;
    reg dataready;
    reg stop;
    wire num1_bit;
    wire num2_bit;
    wire select0;
    wire select1;
    wire ok;

    // Instantiate the data_sender module
    memory dut (
        .clk(clk),
        .dataready(dataready),
        .stop(stop),
        .num1_bit(num1_bit),
        .num2_bit(num2_bit),
        .select0(select0),
        .select1(select1),
        .ok(ok)
    );

    // Generate clock signal
    always #5 clk = ~clk;

    initial begin
        // Initialize signals
        clk = 0;
        dataready = 0;
        stop = 0;
        
        // Apply test stimulus
        #10 dataready = 1; // Trigger data sending
        #10 dataready = 0; // Clear dataready after starting

        // Wait until ok goes high (data is sent)
        wait(ok == 1);
        #10 stop = 1; // Apply stop signal
        #10 stop = 0; // Clear stop signal to allow next transmission

        // Repeat for next data sets
        #50 dataready = 1;
        #10 dataready = 0;
        wait(ok == 1);
        #10 stop = 1;
        #10 stop = 0;

        #50 dataready = 1;
        #10 dataready = 0;
        wait(ok == 1);
        #10 stop = 1;
        #10 stop = 0;

        #100 dataready = 1;
        #10 dataready = 0;
        wait(ok == 1);
        #10 stop = 1;
        #10 stop = 0;

        // End simulation after all data is sent
        #200 $finish;
    end

    // Dump waveform
    initial begin
        $dumpfile("memory_tb.vcd");
        $dumpvars(0, memory_tb);
    end
endmodule

Memory/memory_tb.vcd
$date
	Sat Sep 21 22:44:03 2024
$end
$version
	Icarus Verilog
$end
$timescale
	1ps
$end
$scope module memory_tb $end
$var wire 1 ! select1 $end
$var wire 1 " select0 $end
$var wire 1 # ok $end
$var wire 1 $ num2_bit $end
$var wire 1 % num1_bit $end
$var reg 1 & clk $end
$var reg 1 ' dataready $end
$var reg 1 ( stop $end
$scope module dut $end
$var wire 1 & clk $end
$var wire 1 ' dataready $end
$var wire 1 ( stop $end
$var parameter 2 ) IDLE $end
$var parameter 2 * SEND_DATA $end
$var parameter 2 + WAIT_STOP $end
$var reg 6 , bit_index [5:0] $end
$var reg 2 - data_index [1:0] $end
$var reg 1 % num1_bit $end
$var reg 1 $ num2_bit $end
$var reg 1 # ok $end
$var reg 1 " select0 $end
$var reg 1 ! select1 $end
$var reg 2 . state [1:0] $end
$upscope $end
$upscope $end
$enddefinitions $end
$comment Show the parameter values. $end
$dumpall
b10 +
b1 *
b0 )
$end
#0
$dumpvars
b0 .
b0 -
b0 ,
0(
0'
0&
0%
0$
0#
0"
0!
$end
#5000
1&
#10000
0&
1'
#15000
b1 .
b11111 ,
1&
#20000
0&
0'
#25000
b11110 ,
1&
#30000
0&
#35000
b11101 ,
1$
1%
1&
#40000
0&
#45000
b11100 ,
0$
0%
1&
#50000
0&
#55000
b11011 ,
1&
#60000
0&
#65000
b11010 ,
1&
#70000
0&
#75000
b11001 ,
1&
#80000
0&
#85000
b11000 ,
1&
#90000
0&
#95000
b10111 ,
1$
1&
#100000
0&
#105000
b10110 ,
1&
#110000
0&
#115000
b10101 ,
0$
1%
1&
#120000
0&
#125000
b10100 ,
1$
0%
1&
#130000
0&
#135000
b10011 ,
0$
1&
#140000
0&
#145000
b10010 ,
1$
1%
1&
#150000
0&
#155000
b10001 ,
0%
1&
#160000
0&
#165000
b10000 ,
0$
1&
#170000
0&
#175000
b1111 ,
1$
1&
#180000
0&
#185000
b1110 ,
0$
1%
1&
#190000
0&
#195000
b1101 ,
1&
#200000
0&
#205000
b1100 ,
1&
#210000
0&
#215000
b1011 ,
1&
#220000
0&
#225000
b1010 ,
0%
1&
#230000
0&
#235000
b1001 ,
1$
1%
1&
#240000
0&
#245000
b1000 ,
0%
1&
#250000
0&
#255000
b111 ,
0$
1%
1&
#260000
0&
#265000
b110 ,
1&
#270000
0&
#275000
b101 ,
1$
1&
#280000
0&
#285000
b100 ,
0$
0%
1&
#290000
0&
#295000
b11 ,
1$
1&
#300000
0&
#305000
b10 ,
0$
1&
#310000
0&
#315000
b1 ,
1&
#320000
0&
#325000
b0 ,
1%
1&
#330000
0&
#335000
b10 .
1#
1$
1&
#340000
0&
#345000
b0 .
b1 -
0$
0%
0#
1&
1(
#350000
0&
#355000
1&
0(
#360000
0&
#365000
1&
#370000
0&
#375000
1&
#380000
0&
#385000
1&
#390000
0&
#395000
1&
#400000
0&
#405000
b1 .
1"
b11111 ,
1&
1'
#410000
0&
#415000
b11110 ,
1%
1&
0'
#420000
0&
#425000
b11101 ,
1$
1&
#430000
0&
#435000
b11100 ,
0$
0%
1&
#440000
0&
#445000
b11011 ,
1&
#450000
0&
#455000
b11010 ,
1&
#460000
0&
#465000
b11001 ,
1&
#470000
0&
#475000
b11000 ,
1&
#480000
0&
#485000
b10111 ,
1$
1&
#490000
0&
#495000
b10110 ,
1&
#500000
0&
#505000
b10101 ,
0$
1%
1&
#510000
0&
#515000
b10100 ,
1$
0%
1&
#520000
0&
#525000
b10011 ,
1&
#530000
0&
#535000
b10010 ,
0$
1%
1&
#540000
0&
#545000
b10001 ,
0%
1&
#550000
0&
#555000
b10000 ,
1$
1&
#560000
0&
#565000
b1111 ,
0$
1%
1&
#570000
0&
#575000
b1110 ,
1$
0%
1&
#580000
0&
#585000
b1101 ,
1&
#590000
0&
#595000
b1100 ,
0$
1&
#600000
0&
#605000
b1011 ,
1&
#610000
0&
#615000
b1010 ,
1$
1%
1&
#620000
0&
#625000
b1001 ,
0$
1&
#630000
0&
#635000
b1000 ,
1&
#640000
0&
#645000
b111 ,
1&
#650000
0&
#655000
b110 ,
1$
1&
#660000
0&
#665000
b101 ,
1&
#670000
0&
#675000
b100 ,
0%
1&
#680000
0&
#685000
b11 ,
0$
1%
1&
#690000
0&
#695000
b10 ,
1$
1&
#700000
0&
#705000
b1 ,
0%
1&
#710000
0&
#715000
b0 ,
0$
1%
1&
#720000
0&
#725000
b10 .
1#
1&
#730000
0&
#735000
b0 .
b10 -
0"
0%
0#
1&
1(
#740000
0&
#745000
1&
0(
#750000
0&
#755000
1&
#760000
0&
#765000
1&
#770000
0&
#775000
1&
#780000
0&
#785000
1&
#790000
0&
#795000
b1 .
1!
b11111 ,
1&
1'
#800000
0&
#805000
b11110 ,
1&
0'
#810000
0&
#815000
b11101 ,
1$
1%
1&
#820000
0&
#825000
b11100 ,
0$
0%
1&
#830000
0&
#835000
b11011 ,
1&
#840000
0&
#845000
b11010 ,
1&
#850000
0&
#855000
b11001 ,
1&
#860000
0&
#865000
b11000 ,
1&
#870000
0&
#875000
b10111 ,
1$
1&
#880000
0&
#885000
b10110 ,
0$
1%
1&
#890000
0&
#895000
b10101 ,
1&
#900000
0&
#905000
b10100 ,
1$
0%
1&
#910000
0&
#915000
b10011 ,
0$
1&
#920000
0&
#925000
b10010 ,
1%
1&
#930000
0&
#935000
b10001 ,
0%
1&
#940000
0&
#945000
b10000 ,
1&
#950000
0&
#955000
b1111 ,
1%
1&
#960000
0&
#965000
b1110 ,
0%
1&
#970000
0&
#975000
b1101 ,
1&
#980000
0&
#985000
b1100 ,
1&
#990000
0&
#995000
b1011 ,
1&
#1000000
0&
#1005000
b1010 ,
1%
1&
#1010000
0&
#1015000
b1001 ,
1&
#1020000
0&
#1025000
b1000 ,
1&
#1030000
0&
#1035000
b111 ,
1&
#1040000
0&
#1045000
b110 ,
1&
#1050000
0&
#1055000
b101 ,
1&
#1060000
0&
#1065000
b100 ,
0%
1&
#1070000
0&
#1075000
b11 ,
1%
1&
#1080000
0&
#1085000
b10 ,
1&
#1090000
0&
#1095000
b1 ,
0%
1&
#1100000
0&
#1105000
b0 ,
1%
1&
#1110000
0&
#1115000
b10 .
1#
1&
#1120000
0&
#1125000
b0 .
b11 -
0!
0%
0#
1&
1(
#1130000
0&
#1135000
1&
0(
#1140000
0&
#1145000
1&
#1150000
0&
#1155000
1&
#1160000
0&
#1165000
1&
#1170000
0&
#1175000
1&
#1180000
0&
#1185000
1&
#1190000
0&
#1195000
1&
#1200000
0&
#1205000
1&
#1210000
0&
#1215000
1&
#1220000
0&
#1225000
1&
#1230000
0&
#1235000
b1 .
1!
1"
b11111 ,
1&
1'
#1240000
0&
#1245000
b11110 ,
1%
1&
0'
#1250000
0&
#1255000
b11101 ,
1$
1&
#1260000
0&
#1265000
b11100 ,
0$
0%
1&
#1270000
0&
#1275000
b11011 ,
1&
#1280000
0&
#1285000
b11010 ,
1&
#1290000
0&
#1295000
b11001 ,
1&
#1300000
0&
#1305000
b11000 ,
1&
#1310000
0&
#1315000
b10111 ,
1$
1%
1&
#1320000
0&
#1325000
b10110 ,
0$
0%
1&
#1330000
0&
#1335000
b10101 ,
1&
#1340000
0&
#1345000
b10100 ,
1$
1%
1&
#1350000
0&
#1355000
b10011 ,
0$
0%
1&
#1360000
0&
#1365000
b10010 ,
1$
1&
#1370000
0&
#1375000
b10001 ,
1&
#1380000
0&
#1385000
b10000 ,
0$
1&
#1390000
0&
#1395000
b1111 ,
1&
#1400000
0&
#1405000
b1110 ,
1&
#1410000
0&
#1415000
b1101 ,
1&
#1420000
0&
#1425000
b1100 ,
1&
#1430000
0&
#1435000
b1011 ,
1&
#1440000
0&
#1445000
b1010 ,
1&
#1450000
0&
#1455000
b1001 ,
1&
#1460000
0&
#1465000
b1000 ,
1&
#1470000
0&
#1475000
b111 ,
1&
#1480000
0&
#1485000
b110 ,
1&
#1490000
0&
#1495000
b101 ,
1&
#1500000
0&
#1505000
b100 ,
1&
#1510000
0&
#1515000
b11 ,
1&
#1520000
0&
#1525000
b10 ,
1&
#1530000
0&
#1535000
b1 ,
1&
#1540000
0&
#1545000
b0 ,
1&
#1550000
0&
#1555000
b10 .
1#
1&
#1560000
0&
#1565000
b0 .
b0 -
0!
0"
0#
1&
1(
#1570000
0&
#1575000
1&
0(
