InstructionMemory/instructions.v
module instructions (
    input clk,
    input loadData,
    output reg [31:0] A,
    output reg [31:0] B
);
    // Memory for A and B values
    reg [31:0] A_mem [0:15];
    reg [31:0] B_mem [0:15];
    reg [3:0] index;            // Index for current data
    reg loadData_prev;          // Register to detect edge of loadData
    reg loadData_valid;         // Signal to trigger data transfer

    initial begin
        // Initialize memory
        A_mem[0] = 32'h00000001; B_mem[0] = 32'h00000002;
        A_mem[1] = 32'h00000003; B_mem[1] = 32'h00000004;
        A_mem[2] = 32'h00000005; B_mem[2] = 32'h00000006;
        A_mem[3] = 32'h00000007; B_mem[3] = 32'h00000008;
        index = 0;               // Start at first data pair
        A = 32'b0;
        B = 32'b0;
        loadData_prev = 0;
        loadData_valid = 0;
    end

    // Detect loadData edge
    always @(posedge clk) begin
        if (loadData && !loadData_prev) begin
            // Rising edge of loadData detected
            loadData_valid <= 1;
        end

        // Update loadData_prev to track edge
        loadData_prev <= loadData;

        // Load data on the first rising edge after loadData goes high
        if (loadData_valid) begin
            A <= A_mem[index];
            B <= B_mem[index];
            index <= index + 1;

            if (index == 15) begin
                index <= 0;        // Wrap around if last data is reached
            end

            loadData_valid <= 0;   // Clear valid signal after loading
        end
    end
endmodule

InstructionMemory/instructions_tb.v
`timescale 1ns / 1ps
`include "instructions.v"
module instructions_tb;
    // Testbench signals
    reg clk;
    reg loadData;
    wire [31:0] A;
    wire [31:0] B;

    // Instantiate the module under test (MUT)
    instructions uut (
        .clk(clk),
        .loadData(loadData),
        .A(A),
        .B(B)
    );

    // Clock generation
    initial begin
        clk = 0;
        forever #10 clk = ~clk; // 100 MHz clock (10 ns period)
    end

    // Test procedure
    initial begin
        $dumpfile("instructions_tb.vcd");
        $dumpvars(0, instructions_tb);
        // Initialize signals
        loadData = 0;

        // Wait for a few clock cycles
        #20;

        // Test 1: Load the first data set
        loadData = 1;
        #100; // Hold loadData high for at least one clock cycle
        loadData = 0;
        #50; // Wait for the next data set to be loaded

        // Test 2: Load the next data set
        loadData = 1;
        #15000; // Hold loadData high for at least one clock cycle
        loadData = 0;
        #10000; // Wait for the next data set to be loaded

        // Test 3: Load another data set
        loadData = 1;
        #10000; // Hold loadData high for at least one clock cycle
        loadData = 0;
        #20000; // Wait for the next data set to be loaded

        // Test 4: Attempt rapid toggling of loadData
        loadData = 1;
        #2 loadData = 0; // Short pulse, should be ignored
        #10;
        loadData = 1;
        #10; // Hold for one clock cycle
        loadData = 0;
        #20;

        // End the simulation
        $finish;
    end

    // Monitor the outputs
    initial begin
        $monitor("Time: %0t | loadData: %b | A: %h | B: %h", $time, loadData, A, B);
    end
endmodule

InstructionMemory/instructions_tb.vcd
$date
	Tue Dec 10 19:45:26 2024
$end
$version
	Icarus Verilog
$end
$timescale
	1ps
$end
$scope module instructions_tb $end
$var wire 32 ! B [31:0] $end
$var wire 32 " A [31:0] $end
$var reg 1 # clk $end
$var reg 1 $ loadData $end
$scope module uut $end
$var wire 1 # clk $end
$var wire 1 $ loadData $end
$var reg 32 % A [31:0] $end
$var reg 32 & B [31:0] $end
$var reg 4 ' index [3:0] $end
$var reg 1 ( loadData_prev $end
$var reg 1 ) loadData_valid $end
$upscope $end
$upscope $end
$enddefinitions $end
$comment Show the parameter values. $end
$dumpall
$end
#0
$dumpvars
0)
0(
b0 '
b0 &
b0 %
0$
0#
b0 "
b0 !
$end
#10000
1#
#20000
0#
1$
#30000
1(
1)
1#
#40000
0#
#50000
0)
b1 '
b10 !
b10 &
b1 "
b1 %
1#
#60000
0#
#70000
1#
#80000
0#
#90000
1#
#100000
0#
#110000
1#
#120000
0#
0$
#130000
0(
1#
#140000
0#
#150000
1#
#160000
0#
#170000
1(
1)
1#
1$
#180000
0#
#190000
0)
b10 '
b100 !
b100 &
b11 "
b11 %
1#
