Adder/Adder.v
module Adder (
    input [31:0] A, B,          // IEEE 754 input numbers
    input control, reset,       // Control and reset signals
    output reg [31:0] out,      // IEEE 754 result
    output reg exception        // Exception signal
);
    // Internal signals
    reg [7:0] expA, expB, expOut; // Exponent
    reg [24:0] mantA, mantB, mantOut; // Mantissa (with leading bits)
    reg signA, signB, signOut;   // Sign bits
    reg [7:0] expDiff;

    // Sequential logic triggered by control or reset
    always @(posedge control or posedge reset) begin
        if (reset) begin
            out <= 32'h00000000;      // Reset the output
            exception <= 0;           // Reset exception flag
        end else begin
            // Step 1: Extract sign, exponent, and mantissa
            signA = A[31];
            signB = B[31];
            expA = A[30:23];
            expB = B[30:23];
            mantA = {2'b01, A[22:0]}; // Add 2 leading bits
            mantB = {2'b01, B[22:0]}; // Add 2 leading bits

            // Step 2: Compute exponent difference and align mantissas
            if (expA > expB) begin
                expDiff = expA - expB;
                mantB = mantB >> expDiff;
                expOut = expA;
            end else if (expA < expB) begin
                expDiff = expB - expA;
                mantA = mantA >> expDiff;
                expOut = expB;
            end else begin
                expOut = expA;
            end

            // Step 3: Add mantissas
            mantOut = mantA + mantB;

            // Step 4: Normalize the result
            if (mantOut[24:23] == 2'b11) begin
                mantOut = mantOut >> 1;
                expOut = expOut + 1;
            end else if (mantOut[24:23] == 2'b00) begin
                while (mantOut[23] == 0) begin
                    mantOut = mantOut << 1;
                    expOut = expOut - 1;
                end
            end else if (mantOut[24:23] == 2'b10) begin
                while (mantOut[23] == 0) begin
                    mantOut = mantOut >> 1;
                    expOut = expOut + 1;
                end
            end

            // Step 5: Assemble the final IEEE 754 output
            out <= {signA, expOut, mantOut[22:0]};
            exception <= (expOut == 8'hFF) ? 1 : 0; // Check for overflow
        end
    end
endmodule

Adder/Adder_tb.v
`timescale 10ns / 1ns
`include "Adder.v"

module Adder_tb;
    // Testbench signals
    reg [31:0] A, B;         // Inputs to the adder
    reg control, reset;       // Control and reset signals
    wire [31:0] out;          // Output from the adder
    wire exception;           // Exception signal

    // Instantiate the Adder module
    Adder uut (
        .A(A),
        .B(B),
        .control(control),
        .reset(reset),
        .out(out),
        .exception(exception)
    );

    // Clock generation for control signal (1ms = 1_000_000ns)
    initial begin
        control = 0;
        forever #4 control = ~control;  // Toggle every 500us (1ms period)
    end

    // Test procedure
    initial begin
        $dumpfile("Adder_tb.vcd");
        $dumpvars(0, Adder_tb);
        // Initialize inputs
        reset = 0;
        A = 32'h00000000;
        B = 32'h00000000;
        // Release reset after 1ns
        #1 reset = 1;
        #1 reset = 0;
        // 1st 1ms: A = 0.25, B = 100
        #8;    // Wait for 1ms
        A = 32'h3E800000;  
        B = 32'h42C80000;  
        #8;    // Wait for 1ms
        A = 32'h3FA00000; 
        B = 32'h40200000;  

        #8;    // Wait for 1ms
        A = 32'h42C80000;
        B = 32'h3E800000;

        #8;    // Wait for 1ms
        A = 32'h42C80000;  
        B = 32'h43C80000;

        #8;    // Wait for 1ms
        A = 32'h41c8ff1e; 
        B = 32'h3faeb16d;

        #8;    // Wait for 1ms
        A = 32'h3fa00000; 
        B = 32'h3fa00000;

        #10
        $finish;
    end

    // Monitor output and exceptions
    initial begin
        $monitor("Time: %0t | A: %h | B: %h | Out: %h | Exception: %b", $time, A, B, out, exception);
    end
endmodule

Adder/Adder_tb.vcd
$date
	Fri Oct 18 16:15:06 2024
$end
$version
	Icarus Verilog
$end
$timescale
	1ns
$end
$scope module Adder_tb $end
$var wire 32 ! out [31:0] $end
$var wire 1 " exception $end
$var reg 32 # A [31:0] $end
$var reg 32 $ B [31:0] $end
$var reg 1 % control $end
$var reg 1 & reset $end
$scope module uut $end
$var wire 32 ' A [31:0] $end
$var wire 32 ( B [31:0] $end
$var wire 1 % control $end
$var wire 1 & reset $end
$var reg 1 " exception $end
$var reg 8 ) expA [7:0] $end
$var reg 8 * expB [7:0] $end
$var reg 8 + expDiff [7:0] $end
$var reg 8 , expOut [7:0] $end
$var reg 25 - mantA [24:0] $end
$var reg 25 . mantB [24:0] $end
$var reg 25 / mantOut [24:0] $end
$var reg 32 0 out [31:0] $end
$var reg 1 1 signA $end
$var reg 1 2 signB $end
$upscope $end
$upscope $end
$enddefinitions $end
$comment Show the parameter values. $end
$dumpall
$end
#0
$dumpvars
x2
x1
bx 0
bx /
bx .
bx -
bx ,
bx +
bx *
bx )
b0 (
b0 '
0&
0%
b0 $
b0 #
x"
bx !
$end
#10
0"
b0 !
b0 0
1&
#20
0&
#40
b100000000000000000000000 !
b100000000000000000000000 0
b100000000000000000000000 /
b1 ,
b100000000000000000000000 .
b100000000000000000000000 -
b0 *
b0 )
02
01
1%
#80
0%
#100
b1000010110010000000000000000000 $
b1000010110010000000000000000000 (
b111110100000000000000000000000 #
b111110100000000000000000000000 '
#120
b1000010110010001000000000000000 !
b1000010110010001000000000000000 0
b110010001000000000000000 /
b10000101 ,
b1000000000000000 -
b1000 +
b110010000000000000000000 .
b10000101 *
b1111101 )
1%
#160
0%
#180
b1000000001000000000000000000000 $
b1000000001000000000000000000000 (
b111111101000000000000000000000 #
b111111101000000000000000000000 '
#200
b1000000011100000000000000000000 !
b1000000011100000000000000000000 0
b111100000000000000000000 /
b10000000 ,
b1 +
b101000000000000000000000 .
b10100000000000000000000 -
b10000000 *
b1111111 )
1%
#240
0%
#260
b111110100000000000000000000000 $
b111110100000000000000000000000 (
b1000010110010000000000000000000 #
b1000010110010000000000000000000 '
#280
b1000010110010001000000000000000 !
b1000010110010001000000000000000 0
b110010001000000000000000 /
b10000101 ,
b1000 +
b1000000000000000 .
b110010000000000000000000 -
b1111101 *
b10000101 )
1%
#320
0%
#340
b1000011110010000000000000000000 $
b1000011110010000000000000000000 (
#360
b1000011111110100000000000000000 !
b1000011111110100000000000000000 0
b111110100000000000000000 /
b10000111 ,
b1100100000000000000000 -
b10 +
b110010000000000000000000 .
b10000111 *
1%
#400
0%
#420
b111111101011101011000101101101 $
b111111101011101011000101101101 (
b1000001110010001111111100011110 #
b1000001110010001111111100011110 '
#440
b1000001110100111110101000110100 !
b1000001110100111110101000110100 0
b110100111110101000110100 /
b10000011 ,
b100 +
b10101110101100010110 .
b110010001111111100011110 -
b1111111 *
b10000011 )
1%
#480
0%
#500
b111111101000000000000000000000 $
b111111101000000000000000000000 (
b111111101000000000000000000000 #
b111111101000000000000000000000 '
#520
b1000000001000000000000000000000 !
b1000000001000000000000000000000 0
b101000000000000000000000 /
b10000000 ,
b101000000000000000000000 .
b101000000000000000000000 -
b1111111 )
1%
#560
0%
#600
b101000000000000000000000 /
b10000000 ,
1%
