Divider/New/divider.v
module divider (
    input [31:0] DD,    // Dividend in IEEE-754
    input [31:0] DS,    // Divisor in IEEE-754
    input control,      // Trigger on positive edge
    input reset,        // Reset process on positive edge
    output reg [31:0] out,      // IEEE-754 formatted result
    output reg exception,       // Exception flag
    output reg zeroDiv          // Zero division flag
);

    // Internal signals
    reg [7:0] exp_dd, exp_ds, exp_out;
    reg [23:0] mant_dd, mant_ds;
    reg [24:0] mant_out;
    reg sign_dd, sign_ds, sign_out;
    integer i;

    function [24:0] performDiv;
        input [23:0] DD; // Dividend (24-bit)
        input [23:0] DS; // Divisor (24-bit)

        reg [48:0] dividend; // Extended dividend to handle fraction bits
        reg [48:0] divisor;  // Extended divisor to align for subtraction
        reg [24:0] quotient; // Result (25-bit)
        integer i;

        begin
            // Initialize dividend and divisor
            dividend = {DD, 25'b0}; // Append 25 zeros to dividend for fractional bits
            divisor = {DS, 25'b0}; // Align divisor with the dividend
            quotient = 25'b0;      // Initialize quotient to 0

            // Perform long division for 25 steps (1 integer + 24 fraction bits)
            for (i = 24; i >= 0; i = i - 1) begin
                if (dividend >= divisor) begin
                    dividend = dividend - divisor;
                    quotient[i] = 1'b1; // Set current quotient bit to 1
                end else begin
                    quotient[i] = 1'b0; // Set current quotient bit to 0
                end
                divisor = divisor >> 1; // Shift divisor right by 1 bit
            end

            // Return the final quotient
            performDiv = quotient;
        end
    endfunction

    // Always block for control and reset logic
    always @(posedge control or posedge reset) begin
        if (reset) begin
            out <= 32'b0;
            exception <= 1'b0;
            zeroDiv <= 1'b0;
        end else begin
            // Extract fields
            sign_dd = DD[31];
            sign_ds = DS[31];
            exp_dd = DD[30:23];
            exp_ds = DS[30:23];
            mant_dd = {1'b1, DD[22:0]}; // Normalized mantissa
            mant_ds = {1'b1, DS[22:0]}; // Normalized mantissa

            // Sign of the result
            sign_out = sign_dd ^ sign_ds;

            // Check for division by zero
            if (DS == 0) begin
                zeroDiv <= 1;
                if (DD == 0) begin
                    out <= 32'hFFC00000; // NaN
                    exception <= 1;
                end else begin
                    out <= {sign_out, 8'hFF, 23'b0}; // Infinity
                    exception <= 1;
                end
            end else if (DD == 0) begin
                zeroDiv <= 0;
                exception <= 0;
                out <= 32'h00000000; // Zero result
            end else begin
                zeroDiv <= 0;
                exception <= 0;

                // Exponent calculation
                exp_out = exp_dd - exp_ds + 127;
                mant_out = performDiv(mant_dd, mant_ds);

                if (mant_out[24] == 1) begin
                    out <= {sign_out, exp_out[7:0], mant_out[23:1]};
                end else begin
                    exp_out = exp_out - 1;
                    out <= {sign_out, exp_out[7:0], mant_out[22:0]};
                end
            end
        end
    end
endmodule

Divider/New/divider_tb.v
`timescale 10ns / 1ns
`include "divider.v"

module divider_tb;
    // Testbench signals
    reg [31:0] DD;          // Dividend in IEEE-754
    reg [31:0] DS;          // Divisor in IEEE-754
    reg control;            // Control signal
    reg reset;              // Reset signal
    wire [31:0] out;        // Output from the divider
    wire exception;         // Exception signal
    wire zeroDiv;           // Zero division flag

    // Instantiate the divider module
    divider uut (
        .DD(DD),
        .DS(DS),
        .control(control),
        .reset(reset),
        .out(out),
        .exception(exception),
        .zeroDiv(zeroDiv)
    );

    // Clock generation for control signal
    initial begin
        control = 0;
        forever #10 control = ~control;  // Toggle every 10ns
    end

    // Test procedure
    initial begin
        $dumpfile("divider_tb.vcd");
        $dumpvars(0, divider_tb);

        // Initialize inputs
        reset = 0;
        DD = 32'h00000000;  // Initially zero
        DS = 32'h00000000;  // Initially zero

        // Test Case 1: Division of 2.345 by -365.214
        #5 reset = 1;  // Assert reset
        #5 reset = 0;  // De-assert reset
        DD = 32'h4012C000; // 2.345 in IEEE-754
        DS = 32'hC33B660A; // -365.214 in IEEE-754
        #2000;  // Wait for output to settle

        // Test Case 2: Division of 45.36 by 12
        DD = 32'h42356000; // 45.36 in IEEE-754
        DS = 32'h41400000; // 12 in IEEE-754
        #2000;  // Wait for output to settle

        // End the simulation
        #500 $finish;
    end

    // Monitor output and exceptions
    initial begin
        $monitor("Time: %0t | DD: %h | DS: %h | Out: %h | Exception: %b | ZeroDiv: %b",
                 $time, DD, DS, out, exception, zeroDiv);
    end
endmodule

//10111100101000010011110100011001
//10111100010010000111100010011010

Divider/New/divider_tb.vcd
$date
	Sat Jan 04 01:17:02 2025
$end
$version
	Icarus Verilog
$end
$timescale
	1ns
$end
$scope module divider_tb $end
$var wire 1 ! zeroDiv $end
$var wire 32 " out [31:0] $end
$var wire 1 # exception $end
$var reg 32 $ DD [31:0] $end
$var reg 32 % DS [31:0] $end
$var reg 1 & control $end
$var reg 1 ' reset $end
$scope module uut $end
$var wire 32 ( DD [31:0] $end
$var wire 32 ) DS [31:0] $end
$var wire 1 & control $end
$var wire 1 ' reset $end
$var reg 1 # exception $end
$var reg 8 * exp_dd [7:0] $end
$var reg 8 + exp_ds [7:0] $end
$var reg 8 , exp_out [7:0] $end
$var reg 24 - mant_dd [23:0] $end
$var reg 24 . mant_ds [23:0] $end
$var reg 25 / mant_out [24:0] $end
$var reg 32 0 out [31:0] $end
$var reg 1 1 sign_dd $end
$var reg 1 2 sign_ds $end
$var reg 1 3 sign_out $end
$var reg 1 ! zeroDiv $end
$scope function performDiv $end
$var reg 24 4 DD [23:0] $end
$var reg 24 5 DS [23:0] $end
$var reg 49 6 dividend [48:0] $end
$var reg 49 7 divisor [48:0] $end
$var reg 25 8 quotient [24:0] $end
$var integer 32 9 i [31:0] $end
$upscope $end
$upscope $end
$upscope $end
$enddefinitions $end
$comment Show the parameter values. $end
$dumpall
$end
#0
$dumpvars
bx 9
bx 8
bx 7
bx 6
bx 5
bx 4
x3
x2
x1
bx 0
bx /
bx .
bx -
bx ,
bx +
bx *
b0 )
b0 (
0'
0&
b0 %
b0 $
x#
bx "
x!
$end
#50
0!
0#
b0 "
b0 0
1'
#100
b10111100010010000111100010011001 "
b10111100010010000111100010011001 0
b110010000111100010011001 /
b11111111111111111111111111111111 9
b110010000111100010011001 8
b101110110110011000001010 7
b101101101010100000001100 6
b100100101100000000000000 4
b101110110110011000001010 5
b1111000 ,
13
b101110110110011000001010 .
b100100101100000000000000 -
b10000110 +
b10000000 *
12
01
b11000011001110110110011000001010 %
b11000011001110110110011000001010 )
b1000000000100101100000000000000 $
b1000000000100101100000000000000 (
0'
1&
#200
0&
#300
b11111111111111111111111111111111 9
b110010000111100010011001 8
b101110110110011000001010 7
b101101101010100000001100 6
b1111000 ,
1&
#400
0&
#500
b11111111111111111111111111111111 9
b110010000111100010011001 8
b101110110110011000001010 7
b101101101010100000001100 6
b1111000 ,
1&
#600
0&
#700
b11111111111111111111111111111111 9
b110010000111100010011001 8
b101110110110011000001010 7
b101101101010100000001100 6
b1111000 ,
1&
#800
0&
#900
b11111111111111111111111111111111 9
b110010000111100010011001 8
b101110110110011000001010 7
b101101101010100000001100 6
b1111000 ,
1&
#1000
0&
#1100
b11111111111111111111111111111111 9
b110010000111100010011001 8
b101110110110011000001010 7
b101101101010100000001100 6
b1111000 ,
1&
#1200
0&
#1300
b11111111111111111111111111111111 9
b110010000111100010011001 8
b101110110110011000001010 7
b101101101010100000001100 6
b1111000 ,
1&
#1400
0&
#1500
b11111111111111111111111111111111 9
b110010000111100010011001 8
b101110110110011000001010 7
b101101101010100000001100 6
b1111000 ,
1&
#1600
0&
#1700
b11111111111111111111111111111111 9
b110010000111100010011001 8
b101110110110011000001010 7
b101101101010100000001100 6
b1111000 ,
1&
#1800
0&
#1900
b11111111111111111111111111111111 9
b110010000111100010011001 8
b101110110110011000001010 7
b101101101010100000001100 6
b1111000 ,
1&
#2000
0&
#2100
b11111111111111111111111111111111 9
b110010000111100010011001 8
b101110110110011000001010 7
b101101101010100000001100 6
b1111000 ,
1&
#2200
0&
#2300
b11111111111111111111111111111111 9
b110010000111100010011001 8
b101110110110011000001010 7
b101101101010100000001100 6
b1111000 ,
1&
#2400
0&
#2500
b11111111111111111111111111111111 9
b110010000111100010011001 8
b101110110110011000001010 7
b101101101010100000001100 6
b1111000 ,
1&
#2600
0&
#2700
b11111111111111111111111111111111 9
b110010000111100010011001 8
b101110110110011000001010 7
b101101101010100000001100 6
b1111000 ,
1&
#2800
0&
#2900
b11111111111111111111111111111111 9
b110010000111100010011001 8
b101110110110011000001010 7
b101101101010100000001100 6
b1111000 ,
1&
#3000
0&
#3100
b11111111111111111111111111111111 9
b110010000111100010011001 8
b101110110110011000001010 7
b101101101010100000001100 6
b1111000 ,
1&
#3200
0&
#3300
b11111111111111111111111111111111 9
b110010000111100010011001 8
b101110110110011000001010 7
b101101101010100000001100 6
b1111000 ,
1&
#3400
0&
#3500
b11111111111111111111111111111111 9
b110010000111100010011001 8
b101110110110011000001010 7
b101101101010100000001100 6
b1111000 ,
1&
#3600
0&
#3700
b11111111111111111111111111111111 9
b110010000111100010011001 8
b101110110110011000001010 7
b101101101010100000001100 6
b1111000 ,
1&
#3800
0&
#3900
b11111111111111111111111111111111 9
b110010000111100010011001 8
b101110110110011000001010 7
b101101101010100000001100 6
b1111000 ,
1&
#4000
0&
#4100
b11111111111111111111111111111111 9
b110010000111100010011001 8
b101110110110011000001010 7
b101101101010100000001100 6
b1111000 ,
1&
#4200
0&
#4300
b11111111111111111111111111111111 9
b110010000111100010011001 8
b101110110110011000001010 7
b101101101010100000001100 6
b1111000 ,
1&
#4400
0&
#4500
b11111111111111111111111111111111 9
b110010000111100010011001 8
b101110110110011000001010 7
b101101101010100000001100 6
b1111000 ,
1&
#4600
0&
#4700
b11111111111111111111111111111111 9
b110010000111100010011001 8
b101110110110011000001010 7
b101101101010100000001100 6
b1111000 ,
1&
#4800
0&
#4900
b11111111111111111111111111111111 9
b110010000111100010011001 8
b101110110110011000001010 7
b101101101010100000001100 6
b1111000 ,
1&
#5000
0&
#5100
b11111111111111111111111111111111 9
b110010000111100010011001 8
b101110110110011000001010 7
b101101101010100000001100 6
b1111000 ,
1&
#5200
0&
#5300
b11111111111111111111111111111111 9
b110010000111100010011001 8
b101110110110011000001010 7
b101101101010100000001100 6
b1111000 ,
1&
#5400
0&
#5500
b11111111111111111111111111111111 9
b110010000111100010011001 8
b101110110110011000001010 7
b101101101010100000001100 6
b1111000 ,
1&
#5600
0&
#5700
b11111111111111111111111111111111 9
b110010000111100010011001 8
b101110110110011000001010 7
b101101101010100000001100 6
b1111000 ,
1&
#5800
0&
#5900
b11111111111111111111111111111111 9
b110010000111100010011001 8
b101110110110011000001010 7
b101101101010100000001100 6
b1111000 ,
1&
#6000
0&
#6100
b11111111111111111111111111111111 9
b110010000111100010011001 8
b101110110110011000001010 7
b101101101010100000001100 6
b1111000 ,
1&
#6200
0&
#6300
b11111111111111111111111111111111 9
b110010000111100010011001 8
b101110110110011000001010 7
b101101101010100000001100 6
b1111000 ,
1&
#6400
0&
#6500
b11111111111111111111111111111111 9
b110010000111100010011001 8
b101110110110011000001010 7
b101101101010100000001100 6
b1111000 ,
1&
#6600
0&
#6700
b11111111111111111111111111111111 9
b110010000111100010011001 8
b101110110110011000001010 7
b101101101010100000001100 6
b1111000 ,
1&
#6800
0&
#6900
b11111111111111111111111111111111 9
b110010000111100010011001 8
b101110110110011000001010 7
b101101101010100000001100 6
b1111000 ,
1&
#7000
0&
#7100
b11111111111111111111111111111111 9
b110010000111100010011001 8
b101110110110011000001010 7
b101101101010100000001100 6
b1111000 ,
1&
#7200
0&
#7300
b11111111111111111111111111111111 9
b110010000111100010011001 8
b101110110110011000001010 7
b101101101010100000001100 6
b1111000 ,
1&
#7400
0&
#7500
b11111111111111111111111111111111 9
b110010000111100010011001 8
b101110110110011000001010 7
b101101101010100000001100 6
b1111000 ,
1&
#7600
0&
#7700
b11111111111111111111111111111111 9
b110010000111100010011001 8
b101110110110011000001010 7
b101101101010100000001100 6
b1111000 ,
1&
#7800
0&
#7900
b11111111111111111111111111111111 9
b110010000111100010011001 8
b101110110110011000001010 7
b101101101010100000001100 6
b1111000 ,
1&
#8000
0&
#8100
b11111111111111111111111111111111 9
b110010000111100010011001 8
b101110110110011000001010 7
b101101101010100000001100 6
b1111000 ,
1&
#8200
0&
#8300
b11111111111111111111111111111111 9
b110010000111100010011001 8
b101110110110011000001010 7
b101101101010100000001100 6
b1111000 ,
1&
#8400
0&
#8500
b11111111111111111111111111111111 9
b110010000111100010011001 8
b101110110110011000001010 7
b101101101010100000001100 6
b1111000 ,
1&
#8600
0&
#8700
b11111111111111111111111111111111 9
b110010000111100010011001 8
b101110110110011000001010 7
b101101101010100000001100 6
b1111000 ,
1&
#8800
0&
#8900
b11111111111111111111111111111111 9
b110010000111100010011001 8
b101110110110011000001010 7
b101101101010100000001100 6
b1111000 ,
1&
#9000
0&
#9100
b11111111111111111111111111111111 9
b110010000111100010011001 8
b101110110110011000001010 7
b101101101010100000001100 6
b1111000 ,
1&
#9200
0&
#9300
b11111111111111111111111111111111 9
b110010000111100010011001 8
b101110110110011000001010 7
b101101101010100000001100 6
b1111000 ,
1&
#9400
0&
#9500
b11111111111111111111111111111111 9
b110010000111100010011001 8
b101110110110011000001010 7
b101101101010100000001100 6
b1111000 ,
1&
#9600
0&
#9700
b11111111111111111111111111111111 9
b110010000111100010011001 8
b101110110110011000001010 7
b101101101010100000001100 6
b1111000 ,
1&
#9800
0&
#9900
b11111111111111111111111111111111 9
b110010000111100010011001 8
b101110110110011000001010 7
b101101101010100000001100 6
b1111000 ,
1&
#10000
0&
#10100
b11111111111111111111111111111111 9
b110010000111100010011001 8
b101110110110011000001010 7
b101101101010100000001100 6
b1111000 ,
1&
#10200
0&
#10300
b11111111111111111111111111111111 9
b110010000111100010011001 8
b101110110110011000001010 7
b101101101010100000001100 6
b1111000 ,
1&
#10400
0&
#10500
b11111111111111111111111111111111 9
b110010000111100010011001 8
b101110110110011000001010 7
b101101101010100000001100 6
b1111000 ,
1&
#10600
0&
#10700
b11111111111111111111111111111111 9
b110010000111100010011001 8
b101110110110011000001010 7
b101101101010100000001100 6
b1111000 ,
1&
#10800
0&
#10900
b11111111111111111111111111111111 9
b110010000111100010011001 8
b101110110110011000001010 7
b101101101010100000001100 6
b1111000 ,
1&
#11000
0&
#11100
b11111111111111111111111111111111 9
b110010000111100010011001 8
b101110110110011000001010 7
b101101101010100000001100 6
b1111000 ,
1&
#11200
0&
#11300
b11111111111111111111111111111111 9
b110010000111100010011001 8
b101110110110011000001010 7
b101101101010100000001100 6
b1111000 ,
1&
#11400
0&
#11500
b11111111111111111111111111111111 9
b110010000111100010011001 8
b101110110110011000001010 7
b101101101010100000001100 6
b1111000 ,
1&
#11600
0&
#11700
b11111111111111111111111111111111 9
b110010000111100010011001 8
b101110110110011000001010 7
b101101101010100000001100 6
b1111000 ,
1&
#11800
0&
#11900
b11111111111111111111111111111111 9
b110010000111100010011001 8
b101110110110011000001010 7
b101101101010100000001100 6
b1111000 ,
1&
#12000
0&
#12100
b11111111111111111111111111111111 9
b110010000111100010011001 8
b101110110110011000001010 7
b101101101010100000001100 6
b1111000 ,
1&
#12200
0&
#12300
b11111111111111111111111111111111 9
b110010000111100010011001 8
b101110110110011000001010 7
b101101101010100000001100 6
b1111000 ,
1&
#12400
0&
#12500
b11111111111111111111111111111111 9
b110010000111100010011001 8
b101110110110011000001010 7
b101101101010100000001100 6
b1111000 ,
1&
#12600
0&
#12700
b11111111111111111111111111111111 9
b110010000111100010011001 8
b101110110110011000001010 7
b101101101010100000001100 6
b1111000 ,
1&
#12800
0&
#12900
b11111111111111111111111111111111 9
b110010000111100010011001 8
b101110110110011000001010 7
b101101101010100000001100 6
b1111000 ,
1&
#13000
0&
#13100
b11111111111111111111111111111111 9
b110010000111100010011001 8
b101110110110011000001010 7
b101101101010100000001100 6
b1111000 ,
1&
#13200
0&
#13300
b11111111111111111111111111111111 9
b110010000111100010011001 8
b101110110110011000001010 7
b101101101010100000001100 6
b1111000 ,
1&
#13400
0&
#13500
b11111111111111111111111111111111 9
b110010000111100010011001 8
b101110110110011000001010 7
b101101101010100000001100 6
b1111000 ,
1&
#13600
0&
#13700
b11111111111111111111111111111111 9
b110010000111100010011001 8
b101110110110011000001010 7
b101101101010100000001100 6
b1111000 ,
1&
#13800
0&
#13900
b11111111111111111111111111111111 9
b110010000111100010011001 8
b101110110110011000001010 7
b101101101010100000001100 6
b1111000 ,
1&
#14000
0&
#14100
b11111111111111111111111111111111 9
b110010000111100010011001 8
b101110110110011000001010 7
b101101101010100000001100 6
b1111000 ,
1&
#14200
0&
#14300
b11111111111111111111111111111111 9
b110010000111100010011001 8
b101110110110011000001010 7
b101101101010100000001100 6
b1111000 ,
1&
#14400
0&
#14500
b11111111111111111111111111111111 9
b110010000111100010011001 8
b101110110110011000001010 7
b101101101010100000001100 6
b1111000 ,
1&
#14600
0&
#14700
b11111111111111111111111111111111 9
b110010000111100010011001 8
b101110110110011000001010 7
b101101101010100000001100 6
b1111000 ,
1&
#14800
0&
#14900
b11111111111111111111111111111111 9
b110010000111100010011001 8
b101110110110011000001010 7
b101101101010100000001100 6
b1111000 ,
1&
#15000
0&
#15100
b11111111111111111111111111111111 9
b110010000111100010011001 8
b101110110110011000001010 7
b101101101010100000001100 6
b1111000 ,
1&
#15200
0&
#15300
b11111111111111111111111111111111 9
b110010000111100010011001 8
b101110110110011000001010 7
b101101101010100000001100 6
b1111000 ,
1&
#15400
0&
#15500
b11111111111111111111111111111111 9
b110010000111100010011001 8
b101110110110011000001010 7
b101101101010100000001100 6
b1111000 ,
1&
#15600
0&
#15700
b11111111111111111111111111111111 9
b110010000111100010011001 8
b101110110110011000001010 7
b101101101010100000001100 6
b1111000 ,
1&
#15800
0&
#15900
b11111111111111111111111111111111 9
b110010000111100010011001 8
b101110110110011000001010 7
b101101101010100000001100 6
b1111000 ,
1&
#16000
0&
#16100
b11111111111111111111111111111111 9
b110010000111100010011001 8
b101110110110011000001010 7
b101101101010100000001100 6
b1111000 ,
1&
#16200
0&
#16300
b11111111111111111111111111111111 9
b110010000111100010011001 8
b101110110110011000001010 7
b101101101010100000001100 6
b1111000 ,
1&
#16400
0&
#16500
b11111111111111111111111111111111 9
b110010000111100010011001 8
b101110110110011000001010 7
b101101101010100000001100 6
b1111000 ,
1&
#16600
0&
#16700
b11111111111111111111111111111111 9
b110010000111100010011001 8
b101110110110011000001010 7
b101101101010100000001100 6
b1111000 ,
1&
#16800
0&
#16900
b11111111111111111111111111111111 9
b110010000111100010011001 8
b101110110110011000001010 7
b101101101010100000001100 6
b1111000 ,
1&
#17000
0&
#17100
b11111111111111111111111111111111 9
b110010000111100010011001 8
b101110110110011000001010 7
b101101101010100000001100 6
b1111000 ,
1&
#17200
0&
#17300
b11111111111111111111111111111111 9
b110010000111100010011001 8
b101110110110011000001010 7
b101101101010100000001100 6
b1111000 ,
1&
#17400
0&
#17500
b11111111111111111111111111111111 9
b110010000111100010011001 8
b101110110110011000001010 7
b101101101010100000001100 6
b1111000 ,
1&
#17600
0&
#17700
b11111111111111111111111111111111 9
b110010000111100010011001 8
b101110110110011000001010 7
b101101101010100000001100 6
b1111000 ,
1&
#17800
0&
#17900
b11111111111111111111111111111111 9
b110010000111100010011001 8
b101110110110011000001010 7
b101101101010100000001100 6
b1111000 ,
1&
#18000
0&
#18100
b11111111111111111111111111111111 9
b110010000111100010011001 8
b101110110110011000001010 7
b101101101010100000001100 6
b1111000 ,
1&
#18200
0&
#18300
b11111111111111111111111111111111 9
b110010000111100010011001 8
b101110110110011000001010 7
b101101101010100000001100 6
b1111000 ,
1&
#18400
0&
#18500
b11111111111111111111111111111111 9
b110010000111100010011001 8
b101110110110011000001010 7
b101101101010100000001100 6
b1111000 ,
1&
#18600
0&
#18700
b11111111111111111111111111111111 9
b110010000111100010011001 8
b101110110110011000001010 7
b101101101010100000001100 6
b1111000 ,
1&
#18800
0&
#18900
b11111111111111111111111111111111 9
b110010000111100010011001 8
b101110110110011000001010 7
b101101101010100000001100 6
b1111000 ,
1&
#19000
0&
#19100
b11111111111111111111111111111111 9
b110010000111100010011001 8
b101110110110011000001010 7
b101101101010100000001100 6
b1111000 ,
1&
#19200
0&
#19300
b11111111111111111111111111111111 9
b110010000111100010011001 8
b101110110110011000001010 7
b101101101010100000001100 6
b1111000 ,
1&
#19400
0&
#19500
b11111111111111111111111111111111 9
b110010000111100010011001 8
b101110110110011000001010 7
b101101101010100000001100 6
b1111000 ,
1&
#19600
0&
#19700
b11111111111111111111111111111111 9
b110010000111100010011001 8
b101110110110011000001010 7
b101101101010100000001100 6
b1111000 ,
1&
#19800
0&
#19900
b11111111111111111111111111111111 9
b110010000111100010011001 8
b101110110110011000001010 7
b101101101010100000001100 6
b1111000 ,
1&
#20000
0&
#20100
b1000000011100011101010101010101 "
b1000000011100011101010101010101 0
b111100011101010101010101 /
b11111111111111111111111111111111 9
b111100011101010101010101 8
b110000000000000000000000 7
b100000000000000000000000 6
b101101010110000000000000 4
b110000000000000000000000 5
b10000000 ,
03
b110000000000000000000000 .
b101101010110000000000000 -
b10000010 +
b10000100 *
02
1&
b1000001010000000000000000000000 %
b1000001010000000000000000000000 )
b1000010001101010110000000000000 $
b1000010001101010110000000000000 (
#20200
0&
#20300
b11111111111111111111111111111111 9
b111100011101010101010101 8
b110000000000000000000000 7
b100000000000000000000000 6
b10000000 ,
1&
#20400
0&
#20500
b11111111111111111111111111111111 9
b111100011101010101010101 8
b110000000000000000000000 7
b100000000000000000000000 6
b10000000 ,
1&
#20600
0&
#20700
b11111111111111111111111111111111 9
b111100011101010101010101 8
b110000000000000000000000 7
b100000000000000000000000 6
b10000000 ,
1&
#20800
0&
#20900
b11111111111111111111111111111111 9
b111100011101010101010101 8
b110000000000000000000000 7
b100000000000000000000000 6
b10000000 ,
1&
#21000
0&
#21100
b11111111111111111111111111111111 9
b111100011101010101010101 8
b110000000000000000000000 7
b100000000000000000000000 6
b10000000 ,
1&
#21200
0&
#21300
b11111111111111111111111111111111 9
b111100011101010101010101 8
b110000000000000000000000 7
b100000000000000000000000 6
b10000000 ,
1&
#21400
0&
#21500
b11111111111111111111111111111111 9
b111100011101010101010101 8
b110000000000000000000000 7
b100000000000000000000000 6
b10000000 ,
1&
#21600
0&
#21700
b11111111111111111111111111111111 9
b111100011101010101010101 8
b110000000000000000000000 7
b100000000000000000000000 6
b10000000 ,
1&
#21800
0&
#21900
b11111111111111111111111111111111 9
b111100011101010101010101 8
b110000000000000000000000 7
b100000000000000000000000 6
b10000000 ,
1&
#22000
0&
#22100
b11111111111111111111111111111111 9
b111100011101010101010101 8
b110000000000000000000000 7
b100000000000000000000000 6
b10000000 ,
1&
#22200
0&
#22300
b11111111111111111111111111111111 9
b111100011101010101010101 8
b110000000000000000000000 7
b100000000000000000000000 6
b10000000 ,
1&
#22400
0&
#22500
b11111111111111111111111111111111 9
b111100011101010101010101 8
b110000000000000000000000 7
b100000000000000000000000 6
b10000000 ,
1&
#22600
0&
#22700
b11111111111111111111111111111111 9
b111100011101010101010101 8
b110000000000000000000000 7
b100000000000000000000000 6
b10000000 ,
1&
#22800
0&
#22900
b11111111111111111111111111111111 9
b111100011101010101010101 8
b110000000000000000000000 7
b100000000000000000000000 6
b10000000 ,
1&
#23000
0&
#23100
b11111111111111111111111111111111 9
b111100011101010101010101 8
b110000000000000000000000 7
b100000000000000000000000 6
b10000000 ,
1&
#23200
0&
#23300
b11111111111111111111111111111111 9
b111100011101010101010101 8
b110000000000000000000000 7
b100000000000000000000000 6
b10000000 ,
1&
#23400
0&
#23500
b11111111111111111111111111111111 9
b111100011101010101010101 8
b110000000000000000000000 7
b100000000000000000000000 6
b10000000 ,
1&
#23600
0&
#23700
b11111111111111111111111111111111 9
b111100011101010101010101 8
b110000000000000000000000 7
b100000000000000000000000 6
b10000000 ,
1&
#23800
0&
#23900
b11111111111111111111111111111111 9
b111100011101010101010101 8
b110000000000000000000000 7
b100000000000000000000000 6
b10000000 ,
1&
#24000
0&
#24100
b11111111111111111111111111111111 9
b111100011101010101010101 8
b110000000000000000000000 7
b100000000000000000000000 6
b10000000 ,
1&
#24200
0&
#24300
b11111111111111111111111111111111 9
b111100011101010101010101 8
b110000000000000000000000 7
b100000000000000000000000 6
b10000000 ,
1&
#24400
0&
#24500
b11111111111111111111111111111111 9
b111100011101010101010101 8
b110000000000000000000000 7
b100000000000000000000000 6
b10000000 ,
1&
#24600
0&
#24700
b11111111111111111111111111111111 9
b111100011101010101010101 8
b110000000000000000000000 7
b100000000000000000000000 6
b10000000 ,
1&
#24800
0&
#24900
b11111111111111111111111111111111 9
b111100011101010101010101 8
b110000000000000000000000 7
b100000000000000000000000 6
b10000000 ,
1&
#25000
0&
#25100
b11111111111111111111111111111111 9
b111100011101010101010101 8
b110000000000000000000000 7
b100000000000000000000000 6
b10000000 ,
1&
#25200
0&
#25300
b11111111111111111111111111111111 9
b111100011101010101010101 8
b110000000000000000000000 7
b100000000000000000000000 6
b10000000 ,
1&
#25400
0&
#25500
b11111111111111111111111111111111 9
b111100011101010101010101 8
b110000000000000000000000 7
b100000000000000000000000 6
b10000000 ,
1&
#25600
0&
#25700
b11111111111111111111111111111111 9
b111100011101010101010101 8
b110000000000000000000000 7
b100000000000000000000000 6
b10000000 ,
1&
#25800
0&
#25900
b11111111111111111111111111111111 9
b111100011101010101010101 8
b110000000000000000000000 7
b100000000000000000000000 6
b10000000 ,
1&
#26000
0&
#26100
b11111111111111111111111111111111 9
b111100011101010101010101 8
b110000000000000000000000 7
b100000000000000000000000 6
b10000000 ,
1&
#26200
0&
#26300
b11111111111111111111111111111111 9
b111100011101010101010101 8
b110000000000000000000000 7
b100000000000000000000000 6
b10000000 ,
1&
#26400
0&
#26500
b11111111111111111111111111111111 9
b111100011101010101010101 8
b110000000000000000000000 7
b100000000000000000000000 6
b10000000 ,
1&
#26600
0&
#26700
b11111111111111111111111111111111 9
b111100011101010101010101 8
b110000000000000000000000 7
b100000000000000000000000 6
b10000000 ,
1&
#26800
0&
#26900
b11111111111111111111111111111111 9
b111100011101010101010101 8
b110000000000000000000000 7
b100000000000000000000000 6
b10000000 ,
1&
#27000
0&
#27100
b11111111111111111111111111111111 9
b111100011101010101010101 8
b110000000000000000000000 7
b100000000000000000000000 6
b10000000 ,
1&
#27200
0&
#27300
b11111111111111111111111111111111 9
b111100011101010101010101 8
b110000000000000000000000 7
b100000000000000000000000 6
b10000000 ,
1&
#27400
0&
#27500
b11111111111111111111111111111111 9
b111100011101010101010101 8
b110000000000000000000000 7
b100000000000000000000000 6
b10000000 ,
1&
#27600
0&
#27700
b11111111111111111111111111111111 9
b111100011101010101010101 8
b110000000000000000000000 7
b100000000000000000000000 6
b10000000 ,
1&
#27800
0&
#27900
b11111111111111111111111111111111 9
b111100011101010101010101 8
b110000000000000000000000 7
b100000000000000000000000 6
b10000000 ,
1&
#28000
0&
#28100
b11111111111111111111111111111111 9
b111100011101010101010101 8
b110000000000000000000000 7
b100000000000000000000000 6
b10000000 ,
1&
#28200
0&
#28300
b11111111111111111111111111111111 9
b111100011101010101010101 8
b110000000000000000000000 7
b100000000000000000000000 6
b10000000 ,
1&
#28400
0&
#28500
b11111111111111111111111111111111 9
b111100011101010101010101 8
b110000000000000000000000 7
b100000000000000000000000 6
b10000000 ,
1&
#28600
0&
#28700
b11111111111111111111111111111111 9
b111100011101010101010101 8
b110000000000000000000000 7
b100000000000000000000000 6
b10000000 ,
1&
#28800
0&
#28900
b11111111111111111111111111111111 9
b111100011101010101010101 8
b110000000000000000000000 7
b100000000000000000000000 6
b10000000 ,
1&
#29000
0&
#29100
b11111111111111111111111111111111 9
b111100011101010101010101 8
b110000000000000000000000 7
b100000000000000000000000 6
b10000000 ,
1&
#29200
0&
#29300
b11111111111111111111111111111111 9
b111100011101010101010101 8
b110000000000000000000000 7
b100000000000000000000000 6
b10000000 ,
1&
#29400
0&
#29500
b11111111111111111111111111111111 9
b111100011101010101010101 8
b110000000000000000000000 7
b100000000000000000000000 6
b10000000 ,
1&
#29600
0&
#29700
b11111111111111111111111111111111 9
b111100011101010101010101 8
b110000000000000000000000 7
b100000000000000000000000 6
b10000000 ,
1&
#29800
0&
#29900
b11111111111111111111111111111111 9
b111100011101010101010101 8
b110000000000000000000000 7
b100000000000000000000000 6
b10000000 ,
1&
#30000
0&
#30100
b11111111111111111111111111111111 9
b111100011101010101010101 8
b110000000000000000000000 7
b100000000000000000000000 6
b10000000 ,
1&
#30200
0&
#30300
b11111111111111111111111111111111 9
b111100011101010101010101 8
b110000000000000000000000 7
b100000000000000000000000 6
b10000000 ,
1&
#30400
0&
#30500
b11111111111111111111111111111111 9
b111100011101010101010101 8
b110000000000000000000000 7
b100000000000000000000000 6
b10000000 ,
1&
#30600
0&
#30700
b11111111111111111111111111111111 9
b111100011101010101010101 8
b110000000000000000000000 7
b100000000000000000000000 6
b10000000 ,
1&
#30800
0&
#30900
b11111111111111111111111111111111 9
b111100011101010101010101 8
b110000000000000000000000 7
b100000000000000000000000 6
b10000000 ,
1&
#31000
0&
#31100
b11111111111111111111111111111111 9
b111100011101010101010101 8
b110000000000000000000000 7
b100000000000000000000000 6
b10000000 ,
1&
#31200
0&
#31300
b11111111111111111111111111111111 9
b111100011101010101010101 8
b110000000000000000000000 7
b100000000000000000000000 6
b10000000 ,
1&
#31400
0&
#31500
b11111111111111111111111111111111 9
b111100011101010101010101 8
b110000000000000000000000 7
b100000000000000000000000 6
b10000000 ,
1&
#31600
0&
#31700
b11111111111111111111111111111111 9
b111100011101010101010101 8
b110000000000000000000000 7
b100000000000000000000000 6
b10000000 ,
1&
#31800
0&
#31900
b11111111111111111111111111111111 9
b111100011101010101010101 8
b110000000000000000000000 7
b100000000000000000000000 6
b10000000 ,
1&
#32000
0&
