Adder_substractor/add_sub.v
module add_sub(
    input [31:0] A, B,         // IEEE 754 input numbers
    input control, reset, addsub, // Control, reset, and add/subtract signals
    output reg [31:0] out,     // IEEE 754 result
    output reg exception       // Exception signal
);
    // Internal signals
    reg [7:0] expA, expB, expOut;     // Exponents
    reg [24:0] mantA, mantB, mantOut; // Mantissas (with leading bits)
    reg signA, signB, signOut;        // Signs
    reg [7:0] expDiff;                // Exponent difference
    reg operation;                    // Actual operation: add (0) / subtract (1)

    // Sequential logic triggered by control or reset
    always @(posedge control or posedge reset) begin
        if (reset) begin
            out <= 32'h00000000;  // Reset the output
            exception <= 0;       // Reset exception flag
        end else begin
            // Step 1: Extract sign, exponent, and mantissa
            signA = A[31];
            
            if (addsub) signB = ~B[31]; // Invert sign of B if subtracting
            else signB = B[31];

            expA = A[30:23];
            expB = B[30:23];
            mantA = {2'b01, A[22:0]}; // Add leading bits to mantissa
            mantB = {2'b01, B[22:0]}; // Add leading bits to mantissa

            // Step 2: Align exponents and mantissas
            if (expA > expB) begin
                expDiff = expA - expB;
                mantB = mantB >> expDiff;
                expOut = expA;
            end else begin
                expDiff = expB - expA;
                mantA = mantA >> expDiff;
                expOut = expB;
            end

            // Step 3: Add or subtract mantissas based on signs
            if (signA == signB) begin
                // If signs are the same, perform addition
                mantOut = mantA + mantB;
                signOut = signA;
            end else begin
                // If signs differ, perform subtraction
                if (mantA >= mantB) begin
                    mantOut = mantA - mantB;
                    signOut = signA;
                end else begin
                    mantOut = mantB - mantA;
                    signOut = signB;
                end
            end

            // Step 4: Normalize the result
            if (mantOut[24]) begin
                mantOut = mantOut >> 1;
                expOut = expOut + 1;
            end else begin
                while (mantOut[23] == 0 && expOut > 0) begin
                    mantOut = mantOut << 1;
                    expOut = expOut - 1;
                end
            end

            // Step 5: Assemble the final IEEE 754 result
            out <= {signOut, expOut, mantOut[22:0]};
            exception <= (expOut == 8'hFF); // Set exception on overflow
        end
    end
endmodule

Adder_substractor/add_sub_tb.v
`timescale 10ns / 1ns
`include "add_sub.v"

module add_sub_tb;
    // Testbench signals
    reg [31:0] A, B;         // Inputs to the adder
    reg control, reset;       // Control and reset signals
    reg addsub;               // Add/subtract signal
    wire [31:0] out;          // Output from the adder
    wire exception;           // Exception signal

    add_sub uut (
        .A(A),
        .B(B),
        .control(control),
        .reset(reset),
        .addsub(addsub),
        .out(out),
        .exception(exception)
    );

    initial begin
        control = 0;
        forever #4 control = ~control;  
    end


    initial begin
        $dumpfile("add_sub_tb.vcd");
        $dumpvars(0, add_sub_tb);
 
        reset = 0;
        control = 0;
        addsub = 0;
        A = 32'h00000000;
        B = 32'h00000000;

        #1 reset = 1;
        #1 reset = 0;
   
        #8;     
        A = 32'h3E800000;  
        B = 32'h42C80000;  
        #8;     
        A = 32'h3FA00000; 
        B = 32'h40200000;  

        #8;
        addsub = 1;     
        A = 32'h42C80000;
        B = 32'h3E800000;
        #8 addsub = 0;

        #8;     
        A = 32'h42C80000;  
        B = 32'h43C80000;

        #8;     
        A = 32'h41c8ff1e; 
        B = 32'hbfc74b5a;

        #8;
        addsub = 1;
        A = 32'h3fa00000; 
        B = 32'h3fa00000;

        #10
        $finish;
    end

    initial begin
        $monitor("Time: %0t | A: %h | B: %h | Out: %h | Exception: %b", $time, A, B, out, exception);
    end
endmodule

Adder_substractor/add_sub_tb.vcd
$date
	Thu Oct 24 21:23:22 2024
$end
$version
	Icarus Verilog
$end
$timescale
	1ns
$end
$scope module add_sub_tb $end
$var wire 32 ! out [31:0] $end
$var wire 1 " exception $end
$var reg 32 # A [31:0] $end
$var reg 32 $ B [31:0] $end
$var reg 1 % addsub $end
$var reg 1 & control $end
$var reg 1 ' reset $end
$scope module uut $end
$var wire 32 ( A [31:0] $end
$var wire 32 ) B [31:0] $end
$var wire 1 % addsub $end
$var wire 1 & control $end
$var wire 1 ' reset $end
$var reg 1 " exception $end
$var reg 8 * expA [7:0] $end
$var reg 8 + expB [7:0] $end
$var reg 8 , expDiff [7:0] $end
$var reg 8 - expOut [7:0] $end
$var reg 25 . mantA [24:0] $end
$var reg 25 / mantB [24:0] $end
$var reg 25 0 mantOut [24:0] $end
$var reg 32 1 out [31:0] $end
$var reg 1 2 signA $end
$var reg 1 3 signB $end
$var reg 1 4 signOut $end
$upscope $end
$upscope $end
$enddefinitions $end
$comment Show the parameter values. $end
$dumpall
$end
#0
$dumpvars
x4
x3
x2
bx 1
bx 0
bx /
bx .
bx -
bx ,
bx +
bx *
b0 )
b0 (
0'
0&
0%
b0 $
b0 #
x"
bx !
$end
#10
0"
b0 !
b0 1
1'
#20
0'
#40
b100000000000000000000000 !
b100000000000000000000000 1
04
b100000000000000000000000 0
b1 -
b0 ,
b100000000000000000000000 /
b100000000000000000000000 .
b0 +
b0 *
03
02
1&
#80
0&
#100
b1000010110010000000000000000000 $
b1000010110010000000000000000000 )
b111110100000000000000000000000 #
b111110100000000000000000000000 (
#120
b1000010110010001000000000000000 !
b1000010110010001000000000000000 1
b110010001000000000000000 0
b10000101 -
b1000000000000000 .
b1000 ,
b110010000000000000000000 /
b10000101 +
b1111101 *
1&
#160
0&
#180
b1000000001000000000000000000000 $
b1000000001000000000000000000000 )
b111111101000000000000000000000 #
b111111101000000000000000000000 (
#200
b1000000011100000000000000000000 !
b1000000011100000000000000000000 1
b111100000000000000000000 0
b10000000 -
b1 ,
b101000000000000000000000 /
b10100000000000000000000 .
b10000000 +
b1111111 *
1&
#240
0&
#260
b111110100000000000000000000000 $
b111110100000000000000000000000 )
b1000010110010000000000000000000 #
b1000010110010000000000000000000 (
1%
#280
b1000010110001111000000000000000 !
b1000010110001111000000000000000 1
b110001111000000000000000 0
b10000101 -
b1000 ,
b1000000000000000 /
b110010000000000000000000 .
b1111101 +
b10000101 *
13
1&
#320
0&
#340
0%
#360
b1000010110010001000000000000000 !
b1000010110010001000000000000000 1
b110010001000000000000000 0
b1000000000000000 /
03
1&
#400
0&
#420
b1000011110010000000000000000000 $
b1000011110010000000000000000000 )
#440
b1000011111110100000000000000000 !
b1000011111110100000000000000000 1
b111110100000000000000000 0
b10000111 -
b1100100000000000000000 .
b10 ,
b110010000000000000000000 /
b10000111 +
1&
#480
0&
#500
b10111111110001110100101101011010 $
b10111111110001110100101101011010 )
b1000001110010001111111100011110 #
b1000001110010001111111100011110 (
#520
b1000001101111001000101001101001 !
b1000001101111001000101001101001 1
b101111001000101001101001 0
b10000011 -
b100 ,
b11000111010010110101 /
b110010001111111100011110 .
b1111111 +
b10000011 *
13
1&
#560
0&
#580
b111111101000000000000000000000 $
b111111101000000000000000000000 )
b111111101000000000000000000000 #
b111111101000000000000000000000 (
1%
#600
b0 !
b0 1
b0 0
b0 -
b0 ,
b101000000000000000000000 /
b101000000000000000000000 .
b1111111 *
1&
#640
0&
#680
b0 -
1&
